{
    "problems": [
        {
            "statement": "次の条件によって定められる数列 $ \\{a_n\\} $ の一般項を求めよ。 $$ a_1 = -3, \\quad a_{n+1} =a_n + 4 $$",
            "solution": "$$ a_n = 4n - 7 $$",
            "gpt": "まず与えられた条件を書き直します。  \n初項  \n$$a_1=-3$$  \n漸化式  \n$$a_{n+1}=a_n+4\\quad(n\\ge1)$$  \n\n1. 数列の性質を確認  \n隣り合う項の差が常に $4$ で一定なので、この数列は「公差 $4$ の等差数列」であることが分かります。\n\n2. 等差数列の一般項の形  \n公差を $d$、初項を $a_1$ とすると、等差数列の一般項は  \n$$a_n=a_1+d(n-1)$$  \nで与えられます。\n\n3. 与えられた数列に当てはめる  \n$$a_1=-3,\\; d=4$$  \nしたがって  \n$$a_n=-3+4(n-1)=4n-7$$\n\n4. 数学的帰納法による確認（必要に応じて）  \n(1) 基底：$n=1$ のとき  \n$$a_1=4\\cdot1-7=-3$$  \n条件を満たす。  \n\n(2) 帰納法の仮定：$n=k$ で $a_k=4k-7$ が成り立つとする。  \n\n(3) 帰納法のステップ：  \n$$a_{k+1}=a_k+4=(4k-7)+4=4(k+1)-7$$  \nよって $n=k+1$ でも成立。  \n\n基底と帰納法より、すべての自然数 $n$ で $a_n=4n-7$ が成り立ちます。\n\n5. 結論  \n一般項は  \n$$\\boxed{a_n=4n-7}\\quad(n\\ge1)$$",
            "is_correct": true
        },
        {
            "statement": "次の条件によって定められる数列 $ \\{a_n\\} $ の一般項を求めよ。 $$ a_1 = 4, \\quad 2a_{n+1} + 3a_n = 0 $$",
            "solution": "$$ a_n = 4 \\cdot \\left( -\\frac{3}{2} \\right)^{n-1} $$",
            "gpt": "【解答】\n\n数列 $\\{a_n\\}$ は\n\n$$2a_{n+1}+3a_n=0 \\qquad(n=1,2,3,\\dots)$$\n\nを満たし、初項 $a_1=4$ が与えられています。  \n高校数学で扱う一次漸化式（階差数列）の基本形であり、次の手順で一般項を求めます。\n\n────────────────────\n1．漸化式を解く  \n────────────────────\n\nまず漸化式を $a_{n+1}$ について整理します。\n\n$$2a_{n+1}+3a_n=0 \\;\\Longrightarrow\\; a_{n+1}=-\\frac{3}{2}a_n.$$\n\nよって\n\n$$a_{n+1}=r\\,a_n \\quad\\bigl(r=-\\tfrac32\\bigr)$$\n\nという形の「等比型」の漸化式になりました。このとき\n\n$$a_n=a_1\\,r^{\\,n-1} \\qquad(n\\ge 1)$$\n\nとなることは、帰納法で簡単に示せます（以下に確認します）。\n\n────────────────────\n2．数学的帰納法による一般形の確認  \n────────────────────\n\n帰納法の骨組みは次の通り。\n\n(i) 基底（$n=1$）  \n$$a_1=a_1\\,r^{\\,0}=a_1\\cdot1 \\quad\\text{で成り立つ。}$$\n\n(ii) 帰納法の仮定  \n$n=k$ で $a_k=a_1\\,r^{\\,k-1}$ が成り立つと仮定。\n\n(iii) 帰納法のステップ  \n漸化式 $a_{k+1}=r\\,a_k$ を用いると\n\n$$a_{k+1}=r\\,a_k=r\\,\\bigl(a_1\\,r^{\\,k-1}\\bigr)=a_1\\,r^{\\,k},$$\n\nすなわち $n=k+1$ でも成り立つ。\n\n(i)〜(iii)より、任意の自然数 $n$ で $a_n=a_1\\,r^{\\,n-1}$ が成立。\n\n────────────────────\n3．初項の代入  \n────────────────────\n\n本問では  \n$a_1=4,\\; r=-\\dfrac32$ なので\n\n$$a_n=4\\left(-\\frac32\\right)^{n-1} \\qquad(n=1,2,3,\\dots)$$\n\nとなります。\n\n────────────────────\n4．答案のまとめ  \n────────────────────\n\n一般項は\n\n$$\\boxed{\\,a_n=4\\left(-\\dfrac32\\right)^{n-1}\\,}\\quad(n\\ge1).$$\n\nこの式を漸化式に代入しても確かに $2a_{n+1}+3a_n=0$ が成り立ち、初項も一致するため、これが求める一般項です。",
            "is_correct": true
        },
        {
            "statement": "次の条件によって定められる数列 $ \\{a_n\\} $ の一般項を求めよ。 $$ a_1 = 1, \\quad a_{n+1} = a_n + 2^n - 3n + 1 $$",
            "solution": "$$ a_n = 2^n - \\frac{3}{2}n^2 + \\frac{5}{2}n - 2 $$",
            "gpt": "【解答】\n\n数列 $\\{a_n\\}$ は  \n$$a_1 = 1,\\qquad a_{n+1}=a_n+2^{\\,n}-3n+1\\qquad(n\\ge1)$$  \nで定められている。一般項 $a_n$ を求める。\n\n────────────────────────\n1. 漸化式を累積和に書き換える  \n$n\\;( \\ge1)$ に対して両辺を $k=1$ から $n-1$ まで足し上げると\n\n$$a_n-a_1=\\sum_{k=1}^{n-1}\\bigl(2^{\\,k}-3k+1\\bigr).$$\n\nしたがって\n\n$$a_n=1+\\sum_{k=1}^{n-1}2^{\\,k}-3\\sum_{k=1}^{n-1}k+\\sum_{k=1}^{n-1}1.$$\n\n────────────────────────\n2. 各和を求める  \n(1) 等比数列の和  \n$$\\sum_{k=1}^{n-1}2^{\\,k}=2^{\\,n}-2.$$\n\n(2) 等差数列の和  \n$$\\sum_{k=1}^{n-1}k=\\frac{(n-1)n}{2}.$$\n\n(3) 定数 1 の和  \n$$\\sum_{k=1}^{n-1}1=n-1.$$\n\n────────────────────────\n3. 代入して整理  \n$$\n\\begin{aligned}\na_n &= 1 +(2^{\\,n}-2)-3\\cdot\\frac{(n-1)n}{2}+(n-1)\\\\\n    &= 2^{\\,n}-1-\\frac{3n^2-3n}{2}+n-1\\\\\n    &= 2^{\\,n}+n-2-\\frac{3n^2-3n}{2}\\\\\n    &= 2^{\\,n}-\\frac{3n^2-5n+4}{2}.\n\\end{aligned}\n$$\n\n────────────────────────\n4. 結論  \n$$\\boxed{\\,a_n=2^{\\,n}-\\dfrac{3n^2-5n+4}{2}\\quad(n\\ge1)\\,}$$\n\n────────────────────────\n5. 検算 (任意の 3 項で確認)\n\n$n=1$ : $2^1-\\dfrac{3-5+4}{2}=2-\\dfrac{2}{2}=1$ で $a_1$ に一致。  \n$n=2$ : $2^2-\\dfrac{12-10+4}{2}=4-\\dfrac{6}{2}=1$，漸化式からも $a_2=1$。  \n$n=3$ : $2^3-\\dfrac{27-15+4}{2}=8-\\dfrac{16}{2}=0$，漸化式からも $a_3=0$。  \n\nいずれも一致するので導出した一般項は正しい。",
            "is_correct": true
        },
        {
            "statement": "次の条件によって定められる数列 $ \\{a_n\\} $ の一般項を求めよ。 $$ a_1 = 6, \\quad a_{n+1} = 4a_n - 3 $$",
            "solution": "$$ a_n = 5 \\cdot 4^{n-1} + 1 $$",
            "gpt": "【解答】\n\n数列の漸化式  \n$$a_{n+1}=4a_n-3 \\qquad(n\\ge1), \\qquad a_1=6$$  \nは「一次線形非同次漸化式」です。  \n同次解（特性解）と特別解を求めて一般解を作る、という標準的な手順で解きます。\n\n────────────────────────\n1. 同次方程式の解  \n非同次項（$-3$）を 0 とおいた同次形は  \n$$a_{n+1}=4a_n$$  \nで、これは等比数列なので  \n$$a^{(h)}_n=C\\,4^{\\,n-1}\\quad(C \\text{ は定数})$$  \nが得られます。\n\n────────────────────────\n2. 特別解（定数解）  \n右辺が定数 $-3$ だけなので、特別解を「定数 $p$」と仮定します。  \n$$p =4p-3\\quad\\Longrightarrow\\quad -3p=-3\\quad\\Longrightarrow\\quad p=1.$$\n\n────────────────────────\n3. 一般解  \n$$a_n = a^{(h)}_n + p = C\\,4^{\\,n-1}+1.$$\n\n────────────────────────\n4. 初期条件で定数決定  \n$$a_1=6 \\quad\\Longrightarrow\\quad 6=C\\cdot4^{0}+1=C+1 \\quad\\Longrightarrow\\quad C=5.$$\n\n────────────────────────\n5. 結論  \n$$\\boxed{\\,a_n = 5\\cdot4^{\\,n-1}+1\\quad(n\\ge1)\\,}$$\n\n────────────────────────\n（確認）  \n$n=1$ で $a_1=5\\cdot4^{0}+1=6$ ✔  \n漸化式も  \n$$a_{n+1}=5\\cdot4^{n}+1=4\\bigl(5\\cdot4^{n-1}+1\\bigr)-3=5\\cdot4^{n}+4-3$$\n$$=5\\cdot4^{n}+1=a_{n+1}$$\nとなり成立します。",
            "is_correct": true
        },
        {
            "statement": "次の条件によって定められる数列 $ \\{a_n\\} $ の一般項を求めよ。 $$ a_1 = 1, \\quad a_{n+1} = 3a_n + 4n $$",
            "solution": "$$ a_n = 4 \\cdot 3^{n-1} - 2n - 1 $$",
            "gpt": "【解答】\n\n与えられた漸化式  \n$$a_1=1,\\qquad a_{n+1}=3a_n+4n\\qquad(n=1,2,3,\\dots)$$  \nは 1 次線形非同次漸化式です。  \n一般項 $a_n$ を求めるために，次の２段階で考えます。\n\n(1) 同次部分（右辺の非同次項 $4n$ を取り除いた式）の一般解  \n(2) 非同次部分に対応する特解  \n\n最終的な一般解は「同次解＋特解」で与えられます。\n\n──────────────────────  \n1．同次漸化式の解\n\n非同次項 $4n$ を 0 とおいた同次漸化式は  \n\n$$a_{n+1}^{(h)}=3a_n^{(h)}$$  \n\nで，その解は等比数列  \n\n$$a_n^{(h)}=C\\cdot3^{n-1}\\qquad(Cは定数)$$  \n\nとなります。\n\n──────────────────────  \n2．非同次漸化式の特解\n\n右辺の非同次項が $4n$ （1 次式）なので，特解を「1 次式」の形で仮定します。  \n$$a_n^{(p)}=An+B$$  \nとおいて漸化式に代入します。\n\n左辺：\n$$a_{n+1}^{(p)}=A(n+1)+B=An+A+B$$\n\n右辺：\n$$3a_n^{(p)}+4n=3(An+B)+4n=3An+3B+4n$$\n\n左右の係数を比較すると  \n\n$n$ の係数：  \n$$A = 3A + 4\\qquad\\Longrightarrow\\qquad -2A = 4 \\Longrightarrow A = -2$$\n\n定数項：  \n$$A + B = 3B\\qquad\\Longrightarrow\\qquad -2 + B = 3B \\Longrightarrow -2 = 2B \\Longrightarrow B = -1$$\n\nしたがって特解は  \n\n$$a_n^{(p)}=-2n-1$$\n\n──────────────────────  \n3．一般解と初期条件の適用\n\n一般解は「同次解＋特解」だから  \n\n$$a_n = a_n^{(h)} + a_n^{(p)} \n      = C\\cdot3^{\\,n-1} - 2n - 1$$\n\n初期条件 $a_1=1$ を用いて $C$ を決定します。  \n\n$$a_1 = C\\cdot3^{\\,0} - 2\\cdot1 - 1\n      = C - 3 = 1 \n      \\quad\\Longrightarrow\\quad C = 4$$\n\n──────────────────────  \n4．結論（一般項）\n\nしたがって数列 $\\{a_n\\}$ の一般項は\n\n$$a_n = 4\\cdot3^{\\,n-1} - 2n - 1\\qquad(n=1,2,3,\\dots)$$\n\n（確認）  \n$n=1,2$ を代入してみると  \n・$n=1$: $a_1=4-2-1=1$  \n・$n=2$: $a_2=4\\cdot3 - 4 - 1 = 12-5=7$  \n漸化式の計算 $a_2 = 3a_1 +4\\cdot1 = 3 + 4 = 7$ と一致し，正しいことが確かめられます。",
            "is_correct": true
        },
        {
            "statement": "次の条件によって定められる数列 $ \\{a_n\\} $ の一般項を求めよ。 $$ a_1 = 3, \\quad a_{n+1} = 2a_n + 3^{n+1} $$",
            "solution": "$$ a_n = 3^{n+1} - 3 \\cdot 2^n $$",
            "gpt": "【解答】\n\n与えられた漸化式は\n\n$$a_{n+1}=2a_n+3^{\\,n+1}\\qquad(n\\ge1),\\qquad a_1=3$$\n\nである。  \n右辺に $a_n$ が１次で現れ，かつ定数でない（$n$ に依存する）項 $3^{\\,n+1}$ が付いているので，高校数学で扱う一次線形漸化式\n\n$$a_{n+1}-\\alpha a_n=\\beta_n$$\n\nの形になっている。以下，標準的な解法で一般項を求める。\n\n────────────────────────────\n1．同次方程式（右辺を 0 とした式）の解\n────────────────────────────\n\n$$a_{n+1}-2a_n=0$$\n\nを考える。これは等比数列を与え，解は\n\n$$a_n^{(h)}=C\\,2^{\\,n-1}\\qquad(C\\text{ は定数})$$\n\nとなる。\n\n────────────────────────────\n2．特解の決定\n────────────────────────────\n\n非同次項（右辺）$3^{\\,n+1}$ が指数関数 $3^n$ 型なので，特解 $a_n^{(p)}$ を\n\n$$a_n^{(p)}=k\\,3^{\\,n}$$\n\nと仮定する（$k$ は定数）。これを元の漸化式に代入すると\n\n左辺：$a_{n+1}^{(p)}=k\\,3^{\\,n+1}$  \n右辺：$2a_n^{(p)}+3^{\\,n+1}=2k\\,3^{\\,n}+3^{\\,n+1}$\n\n両辺を $3^{\\,n}$ で割って比較すると\n\n$$3k=2k+3\\quad\\Longrightarrow\\quad k=3.$$\n\nしたがって\n\n$$a_n^{(p)}=3\\cdot3^{\\,n}=3^{\\,n+1}.$$\n\n────────────────────────────\n3．一般解\n────────────────────────────\n\n一次線形漸化式の一般解は  \n「同次方程式の解＋特解」で与えられるから，\n\n$$a_n=C\\,2^{\\,n-1}+3^{\\,n+1}.$$\n\n────────────────────────────\n4．初期条件による定数決定\n────────────────────────────\n\n初期値 $a_1=3$ を代入する。\n\n$$3=C\\,2^{\\,0}+3^{\\,2}=C+9\\quad\\Longrightarrow\\quad C=-6.$$\n\n────────────────────────────\n5．結論（一般項）\n────────────────────────────\n\n$$a_n=-6\\cdot2^{\\,n-1}+3^{\\,n+1}.$$\n\n係数を整理すると\n\n$$\\boxed{\\,a_n=3^{\\,n+1}-3\\cdot2^{\\,n}\\,}\\qquad(n\\ge1).$$\n\n確かめ：  \n$n=1$ で $a_1=3^{2}-3\\cdot2=9-6=3$。  \n漸化式に代入しても等式が成り立つことは直接計算で確認できる。",
            "is_correct": true
        },
        {
            "statement": "次の条件によって定められる数列 $ \\{a_n\\} $ の一般項を求めよ。 $$ a_1 = \\frac{1}{5}, \\quad a_{n+1} = \\frac{ a_n }{ 4a_n - 1 } $$",
            "solution": "$$ a_n = \\frac{ 1 }{ 3 \\cdot (-1)^{n-1} + 2 } $$",
            "gpt": "【解法】\n\n与えられた漸化式  \n$$a_{n+1}= \\frac{a_n}{4a_n-1}\\qquad(n\\ge 1),\\qquad a_1=\\frac15$$  \nを直接扱うより，逆数を取って一次漸化式に変形すると見通しがよくなります。\n\n1. 逆数列を導入  \n　$$b_n=\\frac1{a_n}\\qquad(n\\ge1)$$  \n　とおくと\n　$$b_{n+1}=\\,\\frac1{a_{n+1}}\n            =\\frac{4a_n-1}{a_n}\n            =4-\\frac1{a_n}\n            =4-b_n.$$\n\n　すなわち  \n　$$b_{n+1}=4-b_n\\qquad(n\\ge1),\\qquad b_1=\\frac1{a_1}=5.$$\n\n2. 一次漸化式の解  \n　この漸化式はとても単純で「前項を４から引く」だけです。  \n　$$b_1=5,\\; b_2=4-5=-1,\\; b_3=4-(-1)=5,\\; b_4=4-5=-1,\\;\\dots$$  \n　と 5 と $-1$ が交互に現れることがわかります。  \n　帰納法できちんと示すと\n\n　【帰納法】  \n　仮定：$b_k=\\begin{cases}5&(k\\text{ が奇数})\\\\-1&(k\\text{ が偶数})\\end{cases}$  \n　・$k$ が奇数なら $b_{k+1}=4-b_k=4-5=-1$（偶数に対応）  \n　・$k$ が偶数なら $b_{k+1}=4-b_k=4-(-1)=5$（奇数に対応）  \n　ゆえに成り立つ。\n\n　したがって一般項は  \n　$$b_n=\\begin{cases}\n     5 & (n\\text{ が奇数})\\\\[4pt]\n     -1 & (n\\text{ が偶数})\n   \\end{cases}.$$\n\n3. 元の数列へ戻す  \n　$$a_n=\\frac1{b_n}\n   =\\begin{cases}\n     \\dfrac15 & (n\\text{ が奇数})\\\\[6pt]\n     -1 & (n\\text{ が偶数})\n   \\end{cases}.$$\n\n4. 結論  \n　$$\\boxed{a_n=\n     \\begin{cases}\n       \\dfrac{1}{5} & (n \\text{ が奇数})\\\\[6pt]\n       -1 & (n \\text{ が偶数})\n     \\end{cases}}$$\n\n奇数番目には $\\frac15$，偶数番目には $-1$ が現れ，これ以外の値を取らないことも上記の帰納的議論で保証されています。",
            "is_correct": true
        },
        {
            "statement": "次の条件によって定められる数列 $ \\{a_n\\} $ の一般項を求めよ。 $$ a_1 = 1, \\quad a_{n+1} = 2 \\sqrt{ a_n } $$",
            "solution": "$$ a_n = 2^{ 2 - 2^{ 2-n } } $$",
            "gpt": "解答\n\n1. $\\; \\log_2$ を用いて指数に置き換える  \n   ルートが出てくる漸化式は，指数をとると一次漸化式（等比＋等差型）に変形できることが多い。  \n   $$ b_n = \\log_2 a_n \\quad (n=1,2,\\dots) $$  \n   とおくと\n   $$ a_{n+1}=2\\sqrt{a_n}\n      \\;\\Longrightarrow\\;\n      \\log_2 a_{n+1} = \\log_2\\!\\bigl(2\\sqrt{a_n}\\bigr)\n      = \\log_2 2 + \\frac12\\log_2 a_n\n      = 1+\\frac12 b_n. $$\n   したがって\n   $$ b_{n+1}=1+\\frac12\\,b_n \\qquad(n\\ge1) $$  \n   初期条件は $a_1=1$ だから\n   $$ b_1=\\log_2 1 = 0.$$\n\n2. 一次漸化式 $b_{n+1}=1+\\frac12 b_n$ を解く  \n   定数項を消すために\n   $$ c_n = b_n-2 $$\n   とおくと\n   $$ c_{n+1}=b_{n+1}-2\n            =\\Bigl(1+\\frac12 b_n\\Bigr)-2\n            =\\frac12(b_n-2)\n            =\\frac12 c_n. $$\n   よって\n   $$ c_n = c_1\\Bigl(\\frac12\\Bigr)^{\\,n-1}. $$\n   ここで $c_1=b_1-2=0-2=-2$ なので\n   $$ c_n = -2\\Bigl(\\frac12\\Bigr)^{\\,n-1} = -2^{\\,2-n}. $$\n\n3. 元の $b_n$，さらに $a_n$ を求める  \n   $$ b_n = 2 + c_n = 2 - 2^{\\,2-n}. $$\n   したがって\n   $$ a_n = 2^{\\,b_n} = 2^{\\,2 - 2^{\\,2-n}}. $$\n\n4. 結論  \n   数列 $\\{a_n\\}$ の一般項は  \n   $$ \\boxed{\\,a_n = 2^{\\,2-2^{\\,2-n}}\\quad(n=1,2,\\dots)\\,}. $$\n\n（確認）  \n$n=1$ のとき $a_1=2^{2-2}=1$ で与えられた初項と一致し，  \n漸化式から計算した $a_2=2\\sqrt{1}=2$ も  \n式に代入すると $a_2=2^{2-1}=2$ となり整合する。  \nまた $n\\to\\infty$ で指数 $2-2^{\\,2-n}\\to2$ だから  \n$a_n\\to2^2=4$ とわかり，列は $1,2,2\\sqrt2,\\dots$ と単調増加して $4$ に近づく。",
            "is_correct": true
        },
        {
            "statement": "次の条件によって定められる数列 $ \\{a_n\\} $ の一般項を求めよ。 $$ a_1 = 2, \\quad a_{n+1} = \\frac{ n+2 }{ n }a_n + 1 $$",
            "solution": "$$ a_n = \\frac{ n(3n+1) }{ 2 } $$",
            "gpt": "【解答】\n\n与えられた漸化式は  \n$$a_1 = 2,\\qquad a_{n+1} = \\frac{n+2}{\\,n\\,}a_n + 1\\quad(n\\ge 1)$$  \nである。以下，数列 $\\{a_n\\}$ の一般項を求める。\n\n────────────────────────\n1　数列の差分を観察して形を推測する  \n────────────────────────  \nまず最初の数項を計算する。\n\n\\[\n\\begin{aligned}\na_1 &= 2,\\\\\na_2 &= \\frac{1+2}{1}\\,a_1+1 = 3\\cdot2+1 = 7,\\\\\na_3 &= \\frac{2+2}{2}\\,a_2+1 = 2\\cdot7+1 = 15,\\\\\na_4 &= \\frac{3+2}{3}\\,a_3+1 = \\frac53\\cdot15+1 = 26,\\\\\na_5 &= \\frac{4+2}{4}\\,a_4+1 = \\frac64\\cdot26+1 = 40.\n\\end{aligned}\n\\]\n\n次に 1 次差分 $\\Delta a_n = a_{n+1}-a_n$ を取る。\n\n\\[\n\\Delta a_1 = 5,\\; \\Delta a_2 = 8,\\; \\Delta a_3 = 11,\\; \\Delta a_4 = 14\n\\]\n\nさらに 2 次差分を取ると\n\n\\[\n\\Delta^2 a_1 = 3,\\; \\Delta^2 a_2 = 3,\\; \\Delta^2 a_3 = 3\n\\]\n\nとなり，2 次差分が常に $3$ で一定であることが分かる。  \n2 次差分が一定の数列は次数 2 の多項式（すなわち $\\displaystyle a_n=An^2+Bn+C$ の形）で表されることが高校数学で知られている。\n\n────────────────────────\n2　係数 $A,\\;B,\\;C$ を決定する  \n────────────────────────  \nよって\n$$a_n = An^2 + Bn + C\\qquad (n\\ge 1)$$\nとおける。これを $n=1,2,3$ の値に合わせる。\n\n\\[\n\\begin{cases}\nA + B + C = 2 & (n=1)\\\\\n4A + 2B + C = 7 & (n=2)\\\\\n9A + 3B + C = 15 & (n=3)\n\\end{cases}\n\\]\n\n連立方程式を解く。\n\nまず 1 行目を 2 行目から引くと  \n$3A + B = 5\\quad\\cdots(＊)$\n\nつぎに 2 行目を 3 行目から引くと  \n$5A + B = 8\\quad\\cdots(＊＊)$\n\n$(＊＊) - (＊)$ で  \n$2A = 3 \\Longrightarrow A = \\frac32$\n\nこれを $(＊)$ に代入して  \n$3\\cdot\\frac32 + B = 5 \\;\\Longrightarrow\\; \\frac92 + B = 5 \\;\\Longrightarrow\\; B = \\frac12$\n\n最後に 1 行目に戻して  \n$A+B+C=2 \\;\\Longrightarrow\\; \\frac32 + \\frac12 + C = 2 \\;\\Longrightarrow\\; C = 0$\n\nしたがって\n\n$$a_n = \\frac32\\,n^2 + \\frac12\\,n = \\frac{n(3n+1)}{2} \\qquad (n\\ge 1)$$\n\nとなる。\n\n────────────────────────\n3　求めた式が漸化式を満たすことの確認  \n────────────────────────  \n念のため一般式が元の漸化式を確かに満たすことを確認する。\n\n左辺  \n$$a_{n+1}= \\frac{(n+1)\\{3(n+1)+1\\}}{2}= \\frac{3n^2+7n+4}{2}$$\n\n右辺  \n\\[\n\\frac{n+2}{n}\\,a_n+1\n= \\frac{n+2}{n}\\cdot\\frac{n(3n+1)}{2}+1\n= \\frac{(n+2)(3n+1)}{2}+1\n= \\frac{3n^2+7n+4}{2}.\n\\]\n\n左右が一致するので，確かに漸化式を満たしている。\n\n────────────────────────\n4　結論  \n────────────────────────  \n\n$$\\boxed{\\,a_n = \\dfrac{n(3n+1)}{2}\\,(n\\ge1)\\,}$$\n\nこれが求める一般項である。",
            "is_correct": true
        },
        {
            "statement": "次の条件によって定められる数列 $ \\{a_n\\} $ の一般項を求めよ。 $$ a_1 = \\frac{1}{2}, \\quad (n+1)a_n = (n-1)a_{n-1}, (n\\geqq2) $$",
            "solution": "$$ a_n = \\frac{ 1 }{ n(n+1) } $$",
            "gpt": "【解答】\n\n与えられた漸化式を整理すると  \n$$(n+1)a_n=(n-1)a_{n-1}\\qquad(n\\ge 2)$$  \nすなわち  \n$$a_n=\\frac{n-1}{\\,n+1\\,}\\,a_{n-1}\\qquad(n\\ge 2).$$\n\n1. 連続する項の比の積を取る  \n$n$ が $2,3,\\dots,n$ と変わるときの比をすべて掛け合わせると  \n$$a_n\n   =a_1\\prod_{k=2}^{n}\\frac{k-1}{k+1}\\qquad(n\\ge 2).$$\n\n2. 積の計算  \n添字をそろえやすいように $k-1$ を $j$ と置き換える（$j=k-1$）。  \nすると  \n$$\\prod_{k=2}^{n}\\frac{k-1}{k+1}\n  =\\prod_{j=1}^{\\,n-1}\\frac{j}{j+2}.$$\n\n分子と分母をそれぞれまとめると\n$$\\text{分子}=1\\cdot2\\cdot\\cdots\\cdot(n-1)=(n-1)!,\\qquad\n  \\text{分母}=3\\cdot4\\cdot\\cdots\\cdot(n+1)=\\frac{(n+1)!}{2!}=\\frac{(n+1)!}{2}.$$\n\nよって  \n$$\\prod_{k=2}^{n}\\frac{k-1}{k+1}\n   =\\frac{(n-1)!}{(n+1)!/2}\n   =\\frac{2\\,(n-1)!}{(n+1)!}\n   =\\frac{2}{n(n+1)}.$$\n（最後で $(n+1)!=(n+1)\\,n\\,(n-1)!$ を用いた。）\n\n3. 一般項  \n$$a_n=a_1\\cdot\\frac{2}{n(n+1)}\n      =\\frac{1}{2}\\cdot\\frac{2}{n(n+1)}\n      =\\boxed{\\displaystyle \\frac{1}{n(n+1)}}\\qquad(n\\ge 1).$$\n\n4. 確認  \n$n=1$ では $a_1=1/(1\\cdot2)=1/2$ で与条件と一致。  \nまた漸化式に代入すると  \n$$(n+1)a_n=(n+1)\\frac{1}{n(n+1)}=\\frac{1}{n},\\qquad\n  (n-1)a_{n-1}=(n-1)\\frac{1}{(n-1)n}=\\frac{1}{n},$$\n両辺が等しく条件を満たす。\n\nしたがって、数列 $\\{a_n\\}$ の一般項は $a_n=\\dfrac{1}{n(n+1)}$ である。",
            "is_correct": true
        },
        {
            "statement": "次の条件によって定められる数列 $ \\{a_n\\} $ の一般項を求めよ。 $$ a_1 = 0, \\quad a_2 = 1, \\quad a_{n+2} = a_{n+1} + 6a_n $$",
            "solution": "$$ a_n = \\frac{1}{5} \\{ 3^{n-1} - (-2)^{n-1} \\} $$",
            "gpt": "【解答】\n\n(1) 特性方程式を立てる  \n数列 $\\{a_n\\}$ が\n$$a_{n+2}=a_{n+1}+6a_n\\qquad(n\\ge1)$$\nを満たすとき，試しに $a_n=r^n\\;(r\\ne0)$ とおくと\n$$r^{\\,n+2}=r^{\\,n+1}+6r^{\\,n}\\quad\\Longrightarrow\\quad r^2-r-6=0.$$\nこれを特性方程式と呼ぶ。\n\n(2) 特性方程式の解  \n$$r^2-r-6=(r-3)(r+2)=0\\quad\\Longrightarrow\\quad r=3,\\; -2.$$\n\n(3) 一般解  \n異なる２つの解が得られたので，数列の一般項は\n$$a_n=A\\cdot3^{\\,n}+B\\cdot(-2)^{\\,n}\\qquad(\\text{定数 }A,B).$$\n\n(4) 初期条件で定数を決定  \n$$\n\\begin{cases}\na_1=0 &\\Longrightarrow\\;A\\cdot3^{\\,1}+B\\cdot(-2)^{\\,1}=0\\\\[4pt]\na_2=1 &\\Longrightarrow\\;A\\cdot3^{\\,2}+B\\cdot(-2)^{\\,2}=1\n\\end{cases}\n\\;\\Longleftrightarrow\\;\n\\begin{cases}\n3A-2B=0\\\\\n9A+4B=1\n\\end{cases}\n$$\n１式から $B=\\dfrac{3}{2}A$ を得て２式に代入すると\n$$9A+4\\left(\\dfrac{3}{2}A\\right)=9A+6A=15A=1\\quad\\Longrightarrow\\quad A=\\dfrac1{15},\\;\nB=\\dfrac{3}{2}\\cdot\\dfrac1{15}=\\dfrac1{10}.$$\n\n(5) 一般項  \n以上より\n$$a_n=\\frac1{15}\\,3^{\\,n}+\\frac1{10}\\,(-2)^{\\,n}\n       =\\frac1{30}\\bigl(2\\cdot3^{\\,n}+3\\cdot(-2)^{\\,n}\\bigr)\\qquad(n\\ge1).$$\n\n(6) 確認  \n$n=1,2$ に代入すると  \n$n=1:\\; \\tfrac1{15}\\cdot3+\\tfrac1{10}\\cdot(-2)=0$,  \n$n=2:\\; \\tfrac1{15}\\cdot9+\\tfrac1{10}\\cdot4=1$  \nとなり，初期条件を満たすことが確かめられる。\n\nよって，求める一般項は\n$$\\boxed{\\,a_n=\\dfrac1{15}\\,3^{\\,n}+\\dfrac1{10}\\,(-2)^{\\,n}\\;(n\\ge1)\\,}. $$",
            "is_correct": true
        },
        {
            "statement": "次の条件によって定められる数列 $ \\{a_n\\} $ の一般項を求めよ。 $$ a_1 = 1, \\quad a_2 = 2, \\quad a_{n+2} + 4a_{n+1} - 5a_n = 0 $$",
            "solution": "$$ a_n = \\frac{1}{6} \\{ 7 - (-5)^{n-1} \\} $$",
            "gpt": "【解答】\n\n(1) 特性方程式を立てる  \n漸化式  \n$$a_{n+2}+4a_{n+1}-5a_n=0\\qquad(n\\ge1)$$  \nは一次の定係数線形同次漸化式なので，解の形を $a_n=r^n$ と置くと\n\n$$r^{n+2}+4r^{n+1}-5r^n=0\n\\;\\Longleftrightarrow\\;\nr^n\\bigl(r^2+4r-5\\bigr)=0.$$\n\n$r^n\\ne0$ だから，特性方程式は  \n\n$$r^2+4r-5=0.$$\n\n(2) 根を求める  \n$$r=\\frac{-4\\pm\\sqrt{4^2-4\\!\\cdot\\!1\\!\\cdot\\!(-5)}}{2}\n      =\\frac{-4\\pm\\sqrt{36}}{2}\n      =\\frac{-4\\pm6}{2}\n      \\Longrightarrow\n      r_1=1,\\; r_2=-5.$$\n\n異なる 2 つの実数解をもつので，一般解は\n\n$$a_n=A\\cdot1^n+B\\cdot(-5)^n\n      =A+B(-5)^n\\qquad(n\\ge1).$$\n\n(3) 初期条件で定数 $A,B$ を決定  \n① $n=1$ を代入  \n$$A-5B=1\\qquad\\;(1)$$  \n② $n=2$ を代入  \n$$A+25B=2\\qquad(2)$$  \n\n(1)，(2) を連立すると  \n$$(2)-(1):\\;30B=1\\;\\Longrightarrow\\;B=\\frac1{30},$$\n$$A=1+5B\n     =1+\\frac5{30}\n     =\\frac76.$$\n\n(4) 一般項  \n$$a_n=\\frac76+\\frac{(-5)^n}{30}\\qquad(n\\ge1).$$\n\nこれで，初期条件 $a_1=1,\\;a_2=2$ を満たし，かつ与えられた漸化式を満たす数列の一般項がすべて求められたことが確認できる。",
            "is_correct": true
        },
        {
            "statement": "次の条件によって定められる数列 $\\{a_n\\}$ の一般項を求めよ。 $$ a_1 = 0, \\quad a_2 = 2, \\quad a_{n+2} - 4a_{n+1} + 4a_n = 0 $$",
            "solution": "$$ a_n = (n-1) \\cdot 2^{n-1} $$",
            "gpt": "【解答方針】  \n与えられた漸化式は\n\n$$a_{n+2}-4a_{n+1}+4a_n=0$$\n\nという定係数線形の２次漸化式である。  \n高校数学では「特性方程式」を立てて解く方法が最も基本的である。以下、その手順を丁寧に示す。\n\n────────────────────────────\n1　特性方程式を立てる  \n────────────────────────────  \n漸化式の $a_{n+k}$ を $r^k$ に置き換えて\n\n$$r^2-4r+4=0$$\n\nを得る。これを「特性方程式（特性多項式）」という。\n\n────────────────────────────\n2　特性方程式を解く  \n────────────────────────────  \n$$r^2-4r+4=(r-2)^2=0$$\n\nなので、重解 $r=2$ が１つ（二重根）だけ得られる。\n\n────────────────────────────\n3　一般解の形を決定する  \n────────────────────────────  \n重解を持つ場合、一般解は\n\n$$a_n=(\\alpha+\\beta n)r^{\\,n}$$\n\nとなる（高校教科書に載っている公式）。ここで $r=2$ だから\n\n$$a_n=(\\alpha+\\beta n)2^{\\,n}\\qquad(\\alpha,\\beta は定数)$$\n\n────────────────────────────\n4　初期条件で定数を決定する  \n────────────────────────────\n初期条件は $a_1=0,\\;a_2=2$ である。\n\n(1) $n=1$ を代入  \n$$a_1=0=(\\alpha+\\beta)2^{\\,1}=2(\\alpha+\\beta)$$\n$$\\Rightarrow\\ \\alpha+\\beta=0\\tag{★}$$\n\n(2) $n=2$ を代入  \n$$a_2=2=(\\alpha+2\\beta)2^{\\,2}=4(\\alpha+2\\beta)$$\n$$\\Rightarrow\\ \\alpha+2\\beta=\\frac12\\tag{★★}$$\n\n連立(★)(★★)を解くと\n\n$$\\beta=\\frac12,\\quad\\alpha=-\\frac12$$\n\n────────────────────────────\n5　一般項の完成  \n────────────────────────────  \n求めた $\\alpha,\\beta$ を一般解に戻すと\n\n$$a_n=\\left(-\\frac12+\\frac12 n\\right)2^{\\,n}\n      =\\frac{n-1}{2}\\,2^{\\,n}\n      =(n-1)2^{\\,n-1}$$\n\n────────────────────────────\n6　確認  \n────────────────────────────  \n$n=1$ なら $a_1=(1-1)2^{0}=0$  \n$n=2$ なら $a_2=(2-1)2^{1}=2$  \nどちらも初期条件を満たす。漸化式への代入も簡単に確かめられるので、これが唯一の一般項である。\n\n────────────────────────────\n【結論】\n\n$$\\boxed{\\,a_n=(n-1)2^{\\,n-1}\\,}\\qquad(n\\ge1)$$",
            "is_correct": true
        },
        {
            "statement": "次の条件によって定められる数列 $\\{a_n\\}$ の一般項を求めよ。 $$ a_1 = 1, \\quad a_2 = 1, \\quad a_{n+2} = a_{n+1} + a_n $$",
            "solution": "$$ a_n = \\frac{1}{\\sqrt{5}} \\Biggl\\{ \\left( \\frac{ 1+\\sqrt{5} }{ 2 } \\right)^n - \\left( \\frac{ 1-\\sqrt{5} }{ 2 } \\right)^n \\Biggr\\} $$",
            "gpt": "【解法の方針】  \n与えられた漸化式  \n$$a_{n+2}=a_{n+1}+a_n\\qquad(n\\ge1),\\quad a_1=1,\\;a_2=1$$  \nは「2次の線形同次漸化式（定数係数）」です。  \n高校数学では、次の３手順で一般項を求めるのが標準です。\n\n1. 係数を文字 $r$ とした“特性方程式”を立てる。  \n2. その解（特性根）を使って一般解をつくる。  \n3. 初期条件で任意定数を決定する。\n\n以下、順に説明します。\n\n────────────────────────────\n1. 特性方程式を立てる  \n漸化式は $a_{n+2}-a_{n+1}-a_n=0$ なので、  \n$$r^{n+2}-r^{n+1}-r^{n}=0 \\quad(\\;r\\ne0\\;)\\ \\Longrightarrow\\ r^{2}-r-1=0$$  \nこれを特性方程式と呼びます。\n\n2. 特性方程式を解く  \n$$r^{2}-r-1=0$$  \nに対し、解の公式より  \n$$r=\\frac{1\\pm\\sqrt{1+4}}{2}=\\frac{1\\pm\\sqrt5}{2}$$  \nよって特性根は  \n$$r_1=\\frac{1+\\sqrt5}{2},\\qquad r_2=\\frac{1-\\sqrt5}{2}$$\n\n3. 一般解と初期条件  \n異なる２つの特性根を $r_1,r_2$ とすると、漸化式を満たす数列は  \n$$a_n=A\\,r_1^{\\,n-1}+B\\,r_2^{\\,n-1}\\qquad(n\\ge1)$$  \nの形になります（指数部を $n-1$ とするのは $a_1$ が簡単になるように揃えただけです）。\n\n初期条件で $A,B$ を決定します。  \n・$n=1$ のとき  \n$$a_1=1=A\\,r_1^{\\,0}+B\\,r_2^{\\,0}=A+B$$  \n・$n=2$ のとき  \n$$a_2=1=A\\,r_1^{\\,1}+B\\,r_2^{\\,1}=A\\,r_1+B\\,r_2$$\n\n連立すると  \n$\\begin{cases}\nA+B=1\\\\\nA\\,r_1+B\\,r_2=1\n\\end{cases}$\n\n１式を $B=1-A$ として２式に代入。  \n$$A\\,r_1+(1-A)\\,r_2=1\n\\;\\Longrightarrow\\;\nA(r_1-r_2)=1-r_2$$\n$$\\therefore\\;A=\\dfrac{1-r_2}{r_1-r_2},\n\\quad\nB=1-A=\\dfrac{r_1-1}{r_1-r_2}$$\n\nここで $r_1-r_2=\\sqrt5,\\;1-r_2=1-\\dfrac{1-\\sqrt5}{2}=\\dfrac{1+\\sqrt5}{2}=r_1$ であることから  \n$$A=\\frac{r_1}{\\sqrt5},\\qquad B=-\\frac{r_2}{\\sqrt5}$$\n（注：$r_1-1=\\dfrac{\\sqrt5-1}{2}=-r_2$ を使えば $B$ も同様に求まります。）\n\nしたがって  \n$$a_n=\\frac{r_1}{\\sqrt5}\\,r_1^{\\,n-1}-\\frac{r_2}{\\sqrt5}\\,r_2^{\\,n-1}\n      =\\frac{r_1^{\\,n}-r_2^{\\,n}}{\\sqrt5}$$\n\n────────────────────────────\n【結論】  \n$$\\boxed{\\,a_n=\\dfrac{\\left(\\dfrac{1+\\sqrt5}{2}\\right)^{\\!n}-\\left(\\dfrac{1-\\sqrt5}{2}\\right)^{\\!n}}{\\sqrt5}\\quad(n\\ge1)\\,}$$\n\nこれは「フィボナッチ数列」の一般項としてよく知られる式です。",
            "is_correct": true
        },
        {
            "statement": "次の条件によって定められる数列 $ \\{a_n\\} $ の一般項を求めよ。 $$ a_1 = 2, \\quad a_{n+1} - a_n + \\frac{1}{2} = 0 $$",
            "solution": "$$ a_n = -\\frac{1}{2}n + \\frac{5}{2} $$",
            "gpt": "【解答】\n\n数列 $\\{a_n\\}$ は\n\n$$a_{n+1}-a_n+\\frac12=0 \\qquad(n\\ge1),\\qquad a_1=2$$\n\nで定義されている。  \nまずは漸化式を整理する。\n\n1. 漸化式を解く  \n   $$a_{n+1}-a_n+\\frac12=0$$\n   を\n   $$a_{n+1}=a_n-\\frac12$$\n   と書き換えると，隣り合う項の差が一定であるため，この数列は公差 $-\\dfrac12$ の等差数列であることが分かる。\n\n2. 一般項の公式（等差数列）  \n   等差数列 $A_1, A_2, \\dots$ に対し，公差を $d$，初項を $A_1$ とすると\n   $$A_n=A_1+(n-1)d$$\n   である。本問では $A_1=a_1=2$, $d=-\\dfrac12$ だから\n   $$a_n=2+(n-1)\\!\\left(-\\frac12\\right).$$\n\n3. 整理  \n   $$a_n=2-\\frac{n-1}{2}=2-\\frac n2+\\frac12=\\frac52-\\frac n2=\\frac{5-n}{2}.$$\n\n4. 結論  \n   $$\\boxed{\\,a_n=\\dfrac{5-n}{2}\\,(n\\ge1)\\,}$$\n\nこの式は $n=1$ を代入すると $\\dfrac{5-1}{2}=2$ となり初項を満たし，また\n\n$$a_{n+1}-a_n+\\frac12=\\Bigl(\\frac{5-(n+1)}{2}\\Bigr)-\\Bigl(\\frac{5-n}{2}\\Bigr)+\\frac12\n=-\\frac12+\\frac12=0$$\n\nより漸化式も満たすので，求める一般項は正しい。",
            "is_correct": true
        },
        {
            "statement": "次の条件によって定められる数列 $ \\{a_n\\} $ の一般項を求めよ。 $$ a_1 = -1, \\quad a_{n+1} + a_n = 0 $$",
            "solution": "$$ a_n = (-1)^n $$",
            "gpt": "【解答】\n\nまず与えられた漸化式を整理します。  \n条件  \n$$a_{n+1}+a_n = 0$$  \nを $a_{n+1}$ について解くと\n\n$$a_{n+1} = -\\,a_n \\tag{1}$$  \n\nとなります。以下、この一次漸化式を用いて一般項を求めます。\n\n────────────────\n1. 初項から数項を書き出してみる\n────────────────  \n(1) 式を順に適用すると\n\n・$n=1$ のとき  \n $a_2 = -\\,a_1 = -(-1) = 1$\n\n・$n=2$ のとき  \n $a_3 = -\\,a_2 = -(1) = -1$\n\n・$n=3$ のとき  \n $a_4 = -\\,a_3 = -(-1) = 1$\n\nよって  \n$$-1,\\;1,\\;-1,\\;1,\\;\\dots$$  \nと符号が交互に変わる数列になることが分かります。\n\n────────────────\n2. 帰納法による一般項の導出\n────────────────  \n観察より $a_n$ は $(-1)^n$ になりそうですが、数学的帰納法で確かめます。\n\n命題：$a_n = (-1)^n$ がすべての自然数 $n$ で成り立つ。\n\n(ⅰ) 基底（$n=1$）  \n$a_1 = -1 = (-1)^1$ で成立。\n\n(ⅱ) 帰納ステップ  \n$n=k$ で $a_k = (-1)^k$ が成り立つと仮定する。  \n漸化式 (1) によって\n\n$$a_{k+1} = -\\,a_k = -\\,(-1)^k = (-1)^{k+1}$$  \n\nとなり、$n=k+1$ でも命題が成立する。\n\nよって数学的帰納法により、すべての自然数 $n$ で  \n$$a_n = (-1)^n$$  \nが成り立つ。\n\n────────────────\n3. 結論\n────────────────  \n\n$$\\boxed{\\,a_n = (-1)^n\\quad (n=1,2,3,\\dots)\\,}$$\n\nこれが与えられた条件を満たす数列 $\\{a_n\\}$ の一般項であり、交互に $-1,1,-1,1,\\dots$ と続くことが確認できます。",
            "is_correct": true
        },
        {
            "statement": "次の条件によって定められる数列 $ \\{a_n\\} $ の一般項を求めよ。 $$ a_1 = 3, \\quad 2a_{n+1} - 2a_n = 4n^2 + 2n - 1 $$",
            "solution": "$$ a_n = \\frac{1}{6}( 4n^3 - 3n^2 - 4n + 21 ) $$",
            "gpt": "【解答】\n\n1　漸化式を Δ 形に書き直す  \n与えられた漸化式  \n$$2a_{n+1}-2a_n=4n^2+2n-1\\qquad(n\\ge1)$$  \nを両辺 $2$ で割ると  \n$$a_{n+1}-a_n=2n^2+n-\\frac12\\tag{1}$$  \nとなる。右辺は $n$ の多項式なので、そのまま求和すれば一般項が得られる。\n\n2　両辺を $n=1$ から $n=m$ まで足し合わせる  \n$$\\sum_{n=1}^{m}(a_{n+1}-a_n)=\\sum_{n=1}^{m}\\left(2n^2+n-\\frac12\\right).$$\n\n左辺は望ましい“望遠鏡和”になり  \n$$\\sum_{n=1}^{m}(a_{n+1}-a_n)=a_{m+1}-a_1.$$  \nしたがって  \n$$a_{m+1}=a_1+\\sum_{n=1}^{m}\\left(2n^2+n-\\frac12\\right).\\tag{2}$$\n\n3　右辺の和を計算  \n高校で習う公式  \n$\\displaystyle\\sum_{n=1}^{m}n=\\frac{m(m+1)}2,\\qquad\n\\sum_{n=1}^{m}n^2=\\frac{m(m+1)(2m+1)}6$  \nを用いる。まず\n\n・2次項  \n$$\\sum_{n=1}^{m}2n^2=2\\cdot\\frac{m(m+1)(2m+1)}6=\\frac{m(m+1)(2m+1)}3.$$\n\n・1次項  \n$$\\sum_{n=1}^{m}n=\\frac{m(m+1)}2.$$\n\n・定数項  \n$$\\sum_{n=1}^{m}\\left(-\\frac12\\right)=-\\frac12\\,m.$$\n\nこれらをまとめると  \n$$\\sum_{n=1}^{m}\\left(2n^2+n-\\frac12\\right)\n=\\frac{m(m+1)(2m+1)}3+\\frac{m(m+1)}2-\\frac{m}{2}.\\tag{3}$$\n\n4　$\\,a_{m+1}\\,$（すなわち $\\,a_n\\,$）を得る  \n式 (2)(3) と初期値 $a_1=3$ を用い、$m=n-1$ と置き換えて整理する。\n\n$$a_n\n=3+\\frac{(n-1)n(2n-1)}3+\\frac{(n-1)n}2-\\frac{n-1}{2}.$$\n\n分母を $6$ にそろえて整理すると\n\n$$a_n\n=3+\\frac{2(n-1)n(2n-1)+3(n-1)n-3(n-1)}6\n=3+\\frac{(n-1)\\bigl(4n^2+n-3\\bigr)}6.$$\n\n後ろを展開して分子をまとめると\n\n$$(n-1)(4n^2+n-3)=4n^3-3n^2-4n+3.$$\n\nよって  \n$$a_n=3+\\frac{4n^3-3n^2-4n+3}{6}\n=\\frac{4n^3-3n^2-4n+21}{6}.$$\n\n5　最終結果（整式形に直す）  \n分母を払って係数を簡単に書けば\n\n$$\\boxed{\\,a_n=\\frac{2}{3}n^3-\\frac12 n^2-\\frac23 n+\\frac72\\,}\\qquad(n\\ge1).$$\n\n6　確認  \n$n=1$ のとき  \n$$a_1=\\frac23-\\frac12-\\frac23+\\frac72=3,$$  \n初期値と一致する。また漸化式 (1) への代入でも両辺が等しくなるので、求めた式は確かに一般項である。",
            "is_correct": true
        },
        {
            "statement": "次の条件によって定められる数列 $ \\{a_n\\} $ の一般項を求めよ。 $$ a_1 = 2, \\quad a_{n+1} = 3a_n - 2 $$",
            "solution": "$$ a_n = 3^{n-1} + 1 $$",
            "gpt": "【解答の方針】  \n与えられた漸化式は一次線形型  \n$$a_{n+1}=3a_n-2$$  \nで、定数項が付いています。  \n(1) 同次部分（定数項を無視）を解き、  \n(2) 定数項に対応する特解を求め、  \n(3) 初期条件を使って定数を決定する、  \nという標準的手順で一般項を導きます。\n\n────────────────────────\n1. 同次漸化式の解  \n定数項を 0 として  \n$$a_{n+1}=3a_n$$  \nとおくと、これは等比数列の形なので  \n$$a_n^{(h)}=C\\;3^{\\,n-1}\\quad(C\\text{ は定数})$$  \nが得られます。これを同次解と呼びます。\n\n2. 特解（定数解）を探す  \n右辺が定数 $-2$ なので、定数形の特解を $a_n^{(p)}=A$（$n$ に依らず一定）と仮定すると  \n$$A=3A-2 \\;\\Longrightarrow\\; 2A=2 \\;\\Longrightarrow\\; A=1.$$  \nしたがって特解は $a_n^{(p)}=1$。\n\n3. 一般解  \n同次解と特解の和で  \n$$a_n = a_n^{(h)} + a_n^{(p)} = C\\,3^{\\,n-1}+1.$$\n\n4. 初期条件による定数決定  \n$$a_1=2 \\quad\\Longrightarrow\\quad 2=C\\,3^{\\,0}+1=C+1$$\nより $C=1$。\n\n5. 結論  \n$$\\boxed{\\,a_n=3^{\\,n-1}+1\\,(n\\ge1)\\,}$$\n\n────────────────────────\n【別解・確認：差を取る方法】\n\n数列 $b_n=a_n-1$ を導入すると  \n$$b_{n+1}=a_{n+1}-1=3a_n-2-1=3(a_n-1)=3b_n.$$  \nよって $b_n$ は初項 $b_1=a_1-1=1$、公比 $3$ の等比数列だから  \n$$b_n=3^{\\,n-1}.$$  \n戻して $a_n=b_n+1=3^{\\,n-1}+1$。先ほどと同一の結果が得られます。\n\n────────────────────────\n【帰納法による正当性の確認】\n\n① $n=1$ のとき $a_1=3^{\\,0}+1=2$ で成立。  \n② 帰納法の仮定として $a_k=3^{\\,k-1}+1$ とする。  \n　漸化式より  \n　$a_{k+1}=3a_k-2=3(3^{\\,k-1}+1)-2=3^{\\,k}+1$。  \n　よって $a_{k+1}$ も公式を満たす。  \n③ よってすべての $n$ で公式が成り立つ。\n\n以上で一般項の導出と正当性の証明が完了しました。",
            "is_correct": true
        },
        {
            "statement": "次の条件によって定められる数列 $ \\{a_n\\} $ の一般項を求めよ。 $$ a_1 = 3, \\quad 2a_{n+1} - a_n + 2 = 0 $$",
            "solution": "$$ a_n = 5 \\left( \\frac{1}{2} \\right)^{n-1} - 2 $$",
            "gpt": "【解説】\n\n与えられた漸化式  \n$$2a_{n+1}-a_n+2=0 \\qquad(n=1,2,3,\\dots)$$  \nを整理すると  \n\n$$a_{n+1}=\\frac{a_n-2}{2}=\\frac12\\,a_n-1.$$\n\nこれは「１次の線形漸化式」で、定数項 $-1$ があるためにそのままでは等比型になりません。  \n定数項を消すために、新しい数列 $b_n$ を\n\n$$b_n=a_n+\\alpha$$  \n\nと置き、$\\alpha$ を調整します。\n\n---------\n\n1. 変数変換  \n   $$b_{n+1}=a_{n+1}+\\alpha=\\left(\\frac12\\,a_n-1\\right)+\\alpha\n           =\\frac12(a_n+\\alpha)+\\left(\\alpha-\\frac{\\alpha}{2}-1\\right)\n           =\\frac12\\,b_n+\\left(\\frac{\\alpha}{2}-1-\\alpha\\right).$$  \n\n   この右端の括弧を $0$ にすれば、$b_{n+1}=\\dfrac12\\,b_n$ という等比型になります。  \n   よって  \n   $$\\frac{\\alpha}{2}-1-\\alpha=0 \\quad\\Longrightarrow\\quad -\\frac{\\alpha}{2}=1 \\quad\\Longrightarrow\\quad \\alpha=-2.$$\n\n2. したがって  \n   $$b_n=a_n+2 \\qquad\\text{とすると} \\qquad b_{n+1}=\\frac12\\,b_n.$$\n\n3. 等比数列の一般項  \n   初項は $b_1=a_1+2=3+2=5$ で、公比は $\\dfrac12$。  \n   $$b_n=b_1\\left(\\frac12\\right)^{n-1}=5\\left(\\frac12\\right)^{\\,n-1}=\\frac{5}{2^{\\,n-1}}.$$\n\n4. 元の数列に戻す  \n   $$a_n=b_n-2=\\frac{5}{2^{\\,n-1}}-2.$$\n\n---------\n\n【結論】\n\n$$\\boxed{\\,a_n=\\dfrac{5}{2^{\\,n-1}}-2\\qquad(n=1,2,3,\\dots)\\,}$$\n\n初項 $a_1=3$ も確かに満たしており、漸化式にも代入して確かめることができますから、これが求める一般項です。",
            "is_correct": true
        },
        {
            "statement": "次の条件によって定められる数列 $ \\{a_n\\} $ の一般項を求めよ。 $$ a_1 = -2, \\quad a_{n+1} = -3a_n - 4n + 3 $$",
            "solution": "$$ a_n = -2 \\cdot (-3)^{n-1} - n + 1 $$",
            "gpt": "【解答】\n\n与えられた漸化式  \n$$a_{n+1}=-3a_n-4n+3 \\qquad(n\\ge1),\\qquad a_1=-2$$  \nは「一次不定係数型」の線形漸化式で、高校で習う方法（同次解＋特解）で一般項を決定できる。\n\n────────────────────────────\n1. 同次方程式（右辺の $-4n+3$ を 0 とみなす）\n\n$$a_{n+1}^{(h)}=-3a_n^{(h)}$$\n\nこれは等比数列なので  \n$$a_n^{(h)}=C\\cdot(-3)^{\\,n-1}\\qquad(C\\ \\text{は定数})$$\nが成り立つ。\n\n────────────────────────────\n2. 特解の決定  \n右辺の非同次項 $-4n+3$ は $n$ に一次式である。したがって特解を\n$$a_n^{(p)}=pn+q\\qquad(p,q\\ \\text{は定数})$$\nと仮定して係数を決める。\n\n漸化式に代入すると\n\n左辺：$a_{n+1}^{(p)}=p(n+1)+q=pn+p+q$  \n右辺：$-3a_n^{(p)}-4n+3=-3(pn+q)-4n+3=-3pn-3q-4n+3$\n\nよって $n$ の係数と定数項を比較すると\n\n$\\displaystyle p=-3p-4\\quad\\Longrightarrow\\quad4p=-4\\Longrightarrow p=-1$\n\n$\\displaystyle p+q=-3q+3\\quad\\Longrightarrow\\quad-1+q=-3q+3\\Longrightarrow4q=4\\Longrightarrow q=1$\n\nしたがって特解は  \n$$a_n^{(p)}=-n+1$$\n\n────────────────────────────\n3. 一般解と初期条件の適用\n\n一般解は  \n$$a_n=a_n^{(h)}+a_n^{(p)}=C(-3)^{\\,n-1}+(-n+1)$$\n\n初期値 $a_1=-2$ を代入すると\n\n$-2=C(-3)^{0}+(-1+1)=C+0\\quad\\Longrightarrow\\quad C=-2$\n\nゆえに\n\n$$a_n=-2(-3)^{\\,n-1}-n+1\\qquad(n\\ge1)$$\n\n────────────────────────────\n4. 確認\n\n$n=1$ では $a_1=-2(-3)^0-1+1=-2$ となり、初期値を満たす。  \n漸化式への代入も直接確認できるので、上式はすべての $n\\ge1$ に対して成立する。\n\n────────────────────────────\n【答】  \n$$\\boxed{\\,a_n=-2(-3)^{\\,n-1}-n+1\\quad(n\\ge1)\\,}$$",
            "is_correct": true
        },
        {
            "statement": "次の条件によって定められる数列 $ \\{a_n\\} $ の一般項を求めよ。 $$ a_1 = 4, \\quad a_{n+1} = 4a_n - 2^{n+1} $$",
            "solution": "$$ a_n = 2^{2n-1} + 2^n $$",
            "gpt": "【解説】\n\n数列 $\\{a_n\\}$ は  \n$$a_1=4,\\qquad a_{n+1}=4a_n-2^{\\,n+1}\\qquad(n\\ge1)$$  \nで定まります。これは\n\n　同次部分　$a_{n+1}=4a_n$  \n　非同次項　$-2^{\\,n+1}$  \n\nをもつ１階線形漸化式です。高校数学でよく用いる「同次解 ＋ 特殊解」の方法で一般項を求めます。\n\n────────────────\n1　同次方程式の解  \n────────────────  \n$$a_{n+1}^{(h)}=4a_n^{(h)}$$  \nより、等比数列になりますから\n\n$$a_n^{(h)}=C\\cdot4^{\\,n-1}\\qquad(C：定数)$$\n\n────────────────\n2　特殊解の決定  \n────────────────  \n非同次項が $2^{\\,n+1}$ という指数関数型なので、  \n$$a_n^{(p)}=\\alpha\\;2^{\\,n}\\qquad(\\alpha：定数)$$  \nと仮定します。\n\nこれを漸化式に代入すると\n\n\\[\n\\begin{aligned}\na_{n+1}^{(p)} &= \\alpha\\,2^{\\,n+1},\\\\\n4a_n^{(p)}-2^{\\,n+1} &= 4\\bigl(\\alpha\\,2^{\\,n}\\bigr)-2^{\\,n+1}=4\\alpha\\,2^{\\,n}-2^{\\,n+1}.\n\\end{aligned}\n\\]\n\n両者が等しくなるためには\n\n$$\\alpha\\,2^{\\,n+1}=4\\alpha\\,2^{\\,n}-2^{\\,n+1} \\quad\\Longrightarrow\\quad\n2\\alpha=4\\alpha-2 \\quad\\Longrightarrow\\quad -2\\alpha=-2 \\quad\\Longrightarrow\\quad \\alpha=1.$$\n\nしたがって特殊解は\n\n$$a_n^{(p)}=2^{\\,n}.$$\n\n────────────────\n3　一般解  \n────────────────  \n$$a_n = a_n^{(h)}+a_n^{(p)} = C\\cdot4^{\\,n-1}+2^{\\,n}.$$\n\n────────────────\n4　初期条件で定数 $C$ を決定  \n────────────────  \n$$a_1 = C\\cdot4^{\\,0}+2^{\\,1} = C+2 = 4 \\quad\\Longrightarrow\\quad C=2.$$\n\n────────────────\n5　結論（一般項）  \n────────────────  \n$$a_n = 2\\cdot4^{\\,n-1}+2^{\\,n}.$$\n\n指数を２のべきにまとめると\n\n$$a_n = 2^{2n-1}+2^{\\,n} = 2^{\\,n}\\bigl(2^{\\,n-1}+1\\bigr).$$\n\nどちらの形でもかまいません。以上で数列 $\\{a_n\\}$ の一般項を完全に求めました。",
            "is_correct": true
        },
        {
            "statement": "次の条件によって定められる数列 $ \\{a_n\\} $ の一般項を求めよ。 $$ a_1 = 1, \\quad a_{n+1} = \\frac{ 3a_n }{ 6a_n + 1 } $$",
            "solution": "$$ a_n = \\frac{ 3^{n-1} }{ 3^n - 2 } $$",
            "gpt": "【解答】\n\n手順の概略  \n1. 逆数を取って一次漸化式に帰着させる。  \n2. 一次漸化式を解く（特性方程式＋定数解）。  \n3. 元の $a_n$ に戻し，一般項を整理・確認する。\n\n────────────────────\n\n1. 逆数を置いて漸化式を線形化  \n与えられた漸化式  \n$$a_{n+1}=\\frac{3a_n}{6a_n+1}\\qquad(n\\ge1)$$  \nの両辺を逆数にすると\n\n$$\\frac1{a_{n+1}}=\\frac{6a_n+1}{3a_n}=2+\\frac1{3a_n}.$$\n\nここで  \n$$b_n=\\frac1{a_n} \\quad(n\\ge1)$$  \nとおくと\n\n$$b_{n+1}=2+\\frac13\\,b_n \\qquad(n\\ge1).$$\n\nこれは一次漸化式\n$$b_{n+1}-\\frac13\\,b_n=2$$\nであり，$b_n$ は線形に扱える。\n\n────────────────────\n\n2. $b_n$ の一般項を求める  \n(1) 同次解  \n$$b_{n+1}-\\frac13\\,b_n=0\n\\;\\;\\Longrightarrow\\;\\;\nb_n^{(h)}=C\\!\\left(\\frac13\\right)^{n}.$$\n\n(2) 定数解  \n定数 $k$ を代入すると  \n$$k-\\frac13\\,k=2 \\;\\Longrightarrow\\; \\frac23\\,k=2 \\;\\Longrightarrow\\; k=3.$$\n\n(3) 総合  \n$$b_n=C\\!\\left(\\frac13\\right)^{n}+3.$$\n\n初期条件 $a_1=1$ から  \n$$b_1=\\frac1{a_1}=1\n\\;\\Longrightarrow\\;\n1=C+3 \\;\\Longrightarrow\\; C=-2.$$\n\nしたがって  \n$$b_n=3-2\\!\\left(\\frac13\\right)^{n-1}.$$\n\n────────────────────\n\n3. $a_n$ に戻す  \n$$a_n=\\frac1{b_n}\n       =\\frac1{3-2\\cdot3^{\\,1-n}}\n       =\\frac{3^{\\,n}}{3^{\\,n+1}-6}.$$\n\n分母の $3$ をくくるとさらに\n\n$$a_n=\\frac{3^{\\,n-1}}{3^{\\,n}-2}\n      \\qquad(n\\ge1).$$\n\n────────────────────\n\n4. 確認（帰納的チェック）  \n(i) $n=1$ のとき  \n$$a_1=\\frac{3^{0}}{3^{1}-2}=1$$  \nで初期条件に一致。  \n\n(ii) 一般の $n$ で\n$$a_{n+1}=\\frac{3^{n}}{3^{n+1}-2}.$$\n右辺の式に $a_n=\\dfrac{3^{n-1}}{3^{n}-2}$ を代入すると\n\n$$\\frac{3\\,a_n}{6a_n+1}\n   =\\frac{3\\cdot\\dfrac{3^{n-1}}{3^{n}-2}}\n          {6\\cdot\\dfrac{3^{n-1}}{3^{n}-2}+1}\n   =\\frac{3^{n}}{3^{n+1}-2}\n   =a_{n+1},$$\nで漸化式を満たすことが確かめられる。\n\n────────────────────\n\n【結論】  \n数列 $\\{a_n\\}$ の一般項は  \n\n$$a_n=\\frac{3^{\\,n-1}}{3^{\\,n}-2}\\qquad(n\\ge1).$$",
            "is_correct": true
        },
        {
            "statement": "次の条件によって定められる数列 $ \\{a_n\\} $ の一般項を求めよ。 $$ a_1 = 1, \\quad a_{n+1} = 2a_n^2 $$",
            "solution": "$$ a_n = 2^{ 2^{n-1} - 1 } $$",
            "gpt": "【解答】\n\n(1) まず数列を数えてみる  \n$a_1=1$ だから  \n$a_2=2a_1^2=2$  \n$a_3=2a_2^2=2\\cdot2^2=8$  \n$a_4=2a_3^2=2\\cdot8^2=128$  \n……と急激に大きくなります。規則性を見つけるために対数をとって式を一次化します。\n\n────────────────────\n(2) 対数をとって一次漸化式に直す  \n底は扱いやすい $\\log_2$ を用います。  \n$\\displaystyle c_n=\\log_2 a_n$ とおくと\n\n$$\na_{n+1}=2a_n^2\n\\Longrightarrow \\log_2 a_{n+1}= \\log_2 2 + \\log_2 (a_n^2)\n=1 + 2\\log_2 a_n\n$$\n\nすなわち\n\n$$\nc_{n+1}=1+2c_n \\qquad(n\\ge1)\n$$\n\n初期値 $c_1=\\log_2 a_1=\\log_2 1=0$。\n\n────────────────────\n(3) 一次漸化式 $c_{n+1}=1+2c_n$ を解く  \n\n(i) まず数項を書き出すと  \n$c_1=0,\\; c_2=1,\\; c_3=3,\\; c_4=7,\\ldots$  \n右辺は毎回 “２倍して１を足す” なので  \n$c_n=2^{\\,n-1}-1$ らしき形が見えてきます。\n\n(ii) 数学的帰納法で確認  \n【帰納法の仮定】$c_n=2^{\\,n-1}-1$ とする。  \n【帰納法のステップ】\n\n$$\nc_{n+1}=1+2c_n\n=1+2\\bigl(2^{\\,n-1}-1\\bigr)\n=1+2^{\\,n}-2=2^{\\,n}-1 .\n$$\n\n右辺は $2^{(n+1)-1}-1$ に等しいので成立。  \n初期値 $c_1=0=2^{0}-1$ も満たすから\n\n$$\nc_n=2^{\\,n-1}-1 \\qquad(n\\ge1)\n$$\n\n────────────────────\n(4) 元の数列 $a_n$ に戻す  \n\n$$\na_n=2^{c_n}=2^{\\,2^{\\,n-1}-1}.\n$$\n\n────────────────────\n(5) 結論（一般項）\n\n$$\n\\boxed{\\,a_n=2^{\\,2^{\\,n-1}-1}\\quad(n\\ge1)\\,}\n$$\n\n確認：$n=1$ のとき $a_1=2^{2^{0}-1}=2^{0}=1$（条件と一致）。  \n漸化式も誘導元 $a_{n+1}=2a_n^2$ を満たすことは直接計算すればよいので省略しません：\n\n$$\n2a_n^2\n=2\\bigl(2^{\\,2^{\\,n-1}-1}\\bigr)^2\n=2\\cdot 2^{\\,2\\bigl(2^{\\,n-1}-1\\bigr)}\n=2^{\\,1+2^{\\,n}-2}\n=2^{\\,2^{\\,n}-1}\n=a_{n+1}.\n$$\n\nしたがって答えは正しい。",
            "is_correct": true
        },
        {
            "statement": "次の条件によって定められる数列 $ \\{a_n\\} $ の一般項を求めよ。 $$ a_1 = \\frac{2}{3}, \\quad (n+2)a_n = (n-1)a_{n-1}, (n\\geqq2) $$",
            "solution": "$$ a_n = \\frac{ 4 }{ n(n+1)(n+2) } $$",
            "gpt": "【解答】\n\n1. 漸化式を比の形に書き直す  \n　$$a_n=\\frac{n-1}{n+2}\\,a_{\\,n-1}\\qquad(n\\ge2)$$\n\n2. 積の形で一般化  \n　$n\\ge2$ として  \n　$$a_n=a_{\\,1}\\prod_{k=2}^{n}\\frac{k-1}{k+2}$$\n\n3. 分子と分母をそれぞれまとめる  \n　分子  \n　$$\\prod_{k=2}^{n}(k-1)=\\prod_{j=1}^{n-1}j=(n-1)!$$\n\n　分母  \n　$$\\prod_{k=2}^{n}(k+2)=\\prod_{m=4}^{n+2}m=4\\cdot5\\cdots(n+2)=\\frac{(n+2)!}{3!}$$\n\n4. 積の値を整理  \n　$$\\prod_{k=2}^{n}\\frac{k-1}{k+2}=\\frac{(n-1)!}{(n+2)!/3!}=3!\\,\\frac{(n-1)!}{(n+2)!}$$\n　$$=6\\cdot\\frac{(n-1)!}{(n+2)(n+1)n(n-1)!}=\\frac{6}{n(n+1)(n+2)}$$\n\n5. 初項 $a_1=\\frac23$ を掛ける  \n　$$a_n=a_1\\cdot\\frac{6}{n(n+1)(n+2)}=\\frac{2}{3}\\cdot\\frac{6}{n(n+1)(n+2)}=\\frac{4}{n(n+1)(n+2)}$$\n\n6. $n=1$ で確認  \n　$$a_1=\\frac{4}{1\\cdot2\\cdot3}=\\frac23$$\n　初期条件に一致するので正しい。\n\nしたがって数列 $\\{a_n\\}$ の一般項は\n\n$$\\boxed{a_n=\\dfrac{4}{n(n+1)(n+2)}\\quad(n\\ge1)}$$",
            "is_correct": true
        },
        {
            "statement": "次の条件によって定められる数列 $\\{a_n\\}$ の一般項を求めよ。 $$ a_1 = 1, \\quad a_2 = 2, \\quad a_{n+2} - 2a_{n+1} - 3a_n = 0 $$",
            "solution": "$$ a_n = \\frac{1}{4} { 3^n - (-1)^n } $$",
            "gpt": "【解答】\n\n(1) 特性方程式を立てる  \n与えられた漸化式  \n$$a_{n+2}-2a_{n+1}-3a_n=0 \\qquad(n\\ge1)$$  \nは一次線形同次漸化式（定係数）の形なので，$a_n=r^{\\,n}$ とおいて代入すると\n\n$$r^{\\,n+2}-2r^{\\,n+1}-3r^{\\,n}=0\n\\;\\;\\Longrightarrow\\;\\;\nr^{\\,n}\\bigl(r^2-2r-3\\bigr)=0.$$\n\n$r\\ne0$ なので\n\n$$r^2-2r-3=0$$\n\nを解く。  \n因数分解すると $(r-3)(r+1)=0$ で，根は\n\n$$r_1=3,\\qquad r_2=-1.$$\n\n(2) 一般解の形  \n根が重複していないので，一般項は\n\n$$a_n=A\\cdot3^{\\,n}+B\\cdot(-1)^{\\,n}\\quad(A,Bは定数)$$\n\nとなる。\n\nただし，初項が $n=1$，$n=2$ から始まっているので，指数の合わせ方をそろえておくと便利である。  \nここでは $n=1$ のときに $3^{\\,0}$ や $(-1)^{\\,0}$ になるように\n\n$$a_n=A\\cdot3^{\\,n-1}+B\\cdot(-1)^{\\,n-1}$$\n\nと書いておく。\n\n(3) 初期条件で定数を決定  \n初期条件は $a_1=1,\\;a_2=2$。\n\n① $n=1$ を代入  \n$$a_1=A\\cdot3^{\\,0}+B\\cdot(-1)^{\\,0}=A+B=1\\tag{＊}$$\n\n② $n=2$ を代入  \n$$a_2=A\\cdot3^{\\,1}+B\\cdot(-1)^{\\,1}=3A-B=2\\tag{＊＊}$$\n\n連立すると\n\n$\\begin{cases}\nA+B=1\\\\\n3A-B=2\n\\end{cases}$\n\n加減法で  \n$(＊＊)+(＊):\\;4A=3\\;\\Rightarrow\\;A=\\dfrac34$\n\n$B=1-A=1-\\dfrac34=\\dfrac14$\n\n(4) 一般項の決定  \nよって\n\n$$a_n=\\frac34\\,3^{\\,n-1}+\\frac14\\,(-1)^{\\,n-1}\\quad(n\\ge1)$$\n\nが求める一般項である。\n\n(5) 確認（任意の $n$ で成り立つことのチェック）  \n漸化式に代入してみる：\n\n左辺  \n$a_{n+2}-2a_{n+1}-3a_n\n=\\Bigl(\\frac34\\,3^{\\,n+1}+\\frac14(-1)^{\\,n+1}\\Bigr)\n-2\\Bigl(\\frac34\\,3^{\\,n}+\\frac14(-1)^{\\,n}\\Bigr)\n-3\\Bigl(\\frac34\\,3^{\\,n-1}+\\frac14(-1)^{\\,n-1}\\Bigr).$\n\n3 のべき乗部分だけを見ると\n\n$\\frac34\\bigl(3^{\\,n+1}-2\\cdot3^{\\,n}-3\\cdot3^{\\,n-1}\\bigr)\n=\\frac34\\cdot3^{\\,n-1}(9-6-3)=0.$\n\n同様に $(-1)$ のべき乗部分も\n\n$\\frac14\\bigl((-1)^{\\,n+1}-2(-1)^{\\,n}-3(-1)^{\\,n-1}\\bigr)\n=\\frac14(-1)^{\\,n-1}(-1-2+3)=0.$\n\n両者の和も 0 になるので，漸化式を確かに満たす。\n\nしたがって答えは\n\n$$\\boxed{\\,a_n=\\dfrac34\\;3^{\\,n-1}+\\dfrac14\\,(-1)^{\\,n-1}\\;(n\\ge1)\\,}$$",
            "is_correct": true
        },
        {
            "statement": "次の条件によって定められる数列 $\\{a_n\\}$ の一般項を求めよ。 $$ a_1 = 0, \\quad a_2 = 1, \\quad 5a_{n+2} = 3a_{n+1} + 2a_n $$",
            "solution": "$$ a_n = \\frac{5}{7} \\Biggl\\{ 1 - \\left( -\\frac{2}{5} \\right)^{n-1} \\Biggr\\} $$",
            "gpt": "【解法】\n\n①　漸化式を一次同次形にそろえる  \n与えられた漸化式は  \n$$ 5a_{n+2}=3a_{n+1}+2a_n \\qquad(n\\ge1) $$  \n両辺を $5$ で割ると  \n$$ a_{n+2}=\\frac35\\,a_{n+1}+\\frac25\\,a_n $$  \nこれは一次リニア同次漸化式（係数一定型）なので、特性方程式を用いて一般項を求めることができる。\n\n②　特性方程式を立てて解く  \n特性方程式は  \n$$ r^2-\\frac35\\,r-\\frac25=0 \\quad\\Longleftrightarrow\\quad 5r^2-3r-2=0 $$\n判別式 $D$ を計算すると  \n$$ D=(-3)^2-4\\cdot5\\cdot(-2)=9+40=49=7^2 $$\nよって解は  \n$$ r=\\frac{3\\pm7}{10} $$\nしたがって  \n$$ r_1=1,\\qquad r_2=-\\frac25 $$\n\n③　一般解の形  \n互いに異なる２つの解を得たので、一般項は  \n$$ a_n=A\\cdot1^{\\,n}+B\\left(-\\frac25\\right)^n=A+B\\left(-\\frac25\\right)^n $$  \n($A,\\;B$ は定数)\n\n④　初期条件で定数を決定  \n初期値 $a_1=0,\\;a_2=1$ を代入する。\n\n$n=1$ のとき  \n$$ A+B\\left(-\\frac25\\right)=0\\quad\\Longrightarrow\\quad A-\\frac25B=0\\quad (1) $$\n\n$n=2$ のとき  \n$$ A+B\\left(-\\frac25\\right)^2=A+B\\frac4{25}=1 \\quad (2) $$\n\n(1) から $A=\\dfrac25B$ を (2) に代入すると  \n$$ \\frac25B+B\\frac4{25}=1\\quad\\Longrightarrow\\quad B\\left(\\frac25+\\frac4{25}\\right)=1 $$\n$$ B\\left(\\frac{10}{25}+\\frac{4}{25}\\right)=B\\cdot\\frac{14}{25}=1 $$\n$$ B=\\frac{25}{14} $$\n\nすると  \n$$ A=\\frac25B=\\frac25\\cdot\\frac{25}{14}=\\frac{50}{70}=\\frac57 $$\n\n⑤　一般項  \n求めた $A,\\;B$ を戻すと  \n$$ a_n=\\frac57+\\frac{25}{14}\\left(-\\frac25\\right)^n $$\n\n⑥　形を整える（より簡潔な書き方）  \n$\\displaystyle \\frac{25}{14}\\left(-\\frac25\\right)^n=\\frac57\\left(-\\frac25\\right)^{n-1}$ になるので\n\n$$ \\boxed{\\,a_n=\\frac57\\left(1-\\left(-\\frac25\\right)^{\\,n-1}\\right)\\qquad(n\\ge1)\\,} $$\n\n⑦　確認  \n$n=1$ で $a_1=\\dfrac57\\bigl(1-1\\bigr)=0$，  \n$n=2$ で $a_2=\\dfrac57\\bigl(1+ \\tfrac25 \\bigr)=\\dfrac57\\cdot\\dfrac75=1$  \nいずれも条件を満たすので正しい。",
            "is_correct": true
        },
        {
            "statement": "次の条件によって定められる数列 $\\{a_n\\}$ の一般項を求めよ。 $$ a_1 = 0, \\quad a_2 = 3, \\quad a_{n+2} - 6a_{n+1} + 9a_n = 0 $$",
            "solution": "$$ a_n = (n-1) \\cdot 3^{n-1} $$",
            "gpt": "【解答】\n\n１．漸化式の種類を確認  \n$$a_{n+2}-6a_{n+1}+9a_n=0$$  \nは「２階・線形・斉次・定係数」の漸化式です。したがって「特性方程式」を用いて一般項を求めることができます。\n\n２．特性方程式を立てる  \n$$r^2-6r+9=0$$\n\n３．特性方程式を解く  \n$$r^2-6r+9=(r-3)^2=0 \\Longrightarrow r=3$$  \n重解（重複度２）のみが得られました。\n\n４．重解をもつ場合の一般解  \n重解 $r$ が重複度２で現れたとき，漸化式の一般解は  \n$$a_n=(C_1+C_2n)r^{\\,n}$$  \nで与えられます。ここでは $r=3$ なので  \n$$a_n=(C_1+C_2n)3^{\\,n}$$\n\n５．初期条件で定数を決定  \n(1) $n=1$ のとき  \n$$a_1=0=(C_1+C_2)3^{1}\\quad\\Longrightarrow\\quad C_1+C_2=0$$\n\n(2) $n=2$ のとき  \n$$a_2=3=(C_1+2C_2)3^{2}=9(C_1+2C_2)\\quad\\Longrightarrow\\quad C_1+2C_2=\\frac13$$\n\n１式 $C_1=-C_2$ を２式に代入すると  \n$$-C_2+2C_2=C_2=\\frac13\\quad\\Longrightarrow\\quad C_2=\\frac13,\\; C_1=-\\frac13$$\n\n６．一般項の決定  \n$$a_n=\\left(-\\frac13+\\frac{n}{3}\\right)3^{\\,n}=\\frac{n-1}{3}\\,3^{\\,n}\n     =(n-1)3^{\\,n-1}$$\n\n７．確認  \n$n=1$：$a_1=(1-1)3^{0}=0$  \n$n=2$：$a_2=(2-1)3^{1}=3$  \n漸化式にも代入して成り立つので正しい。\n\n【結論】  \n$$\\boxed{\\,a_n=(n-1)3^{\\,n-1}\\,(n\\ge1)\\,}$$",
            "is_correct": true
        },
        {
            "statement": "次の条件によって定められる数列 $ \\{a_n\\} $ の一般項を求めよ。 $$ a_1 = 1, \\quad a_{n+1} - a_n = 5 $$",
            "solution": "$$ a_n = 5n - 4 $$",
            "gpt": "【解答】\n\n与えられた数列 $\\{a_n\\}$ は  \n$a_1 = 1,\\; a_{n+1}-a_n = 5\\quad(n=1,2,3,\\dots)$  \nという条件で定められています。差が常に一定なので「等差数列」です。\n\n1. 公差（隣り合う項の差）\n   条件より $d = a_{n+1}-a_n = 5$。\n\n2. 等差数列の一般項\n   等差数列では初項を $a_1$、公差を $d$ とすると  \n   $a_n = a_1 + (n-1)d$  \n   となることを思い出します。\n\n3. 当てはめる\n   $a_1 = 1,\\; d = 5$ を代入すると  \n   $$a_n = 1 + (n-1)\\,5 = 1 + 5n - 5 = 5n - 4.$$\n\n4. 確認\n   (i) $n=1$ のとき $a_1 = 5\\cdot1 - 4 = 1$ … 初項に一致。  \n   (ii) 差を取ると  \n   $a_{n+1}-a_n = (5(n+1)-4) - (5n-4) = 5$  \n   条件を満たす。\n\nよって、求める一般項は  \n$$a_n = 5n - 4 \\quad(n=1,2,3,\\dots).$$",
            "is_correct": true
        },
        {
            "statement": "次の条件によって定められる数列 $\\{a_n\\}$ の一般項を求めよ。 $$ a_1 = 4, \\quad a_{n+1} = a_n - 2 $$",
            "solution": "$$ a_n = -2n + 6 $$",
            "gpt": "【解答】\n\nまず、与えられた漸化式  \n$$a_{n+1}=a_n-2 \\qquad(n\\ge1)$$  \nを見ると、各項は前の項から $-2$ ずつ減っていることがわかります。すなわち、本数列 $\\{a_n\\}$ は\n\n　公差 $d=-2$ の等差数列\n\nになっています。\n\n等差数列の一般項の公式  \n$$a_n=a_1+(n-1)d$$  \nに $a_1=4,\\;d=-2$ を代入すると\n\n$$a_n=4+(n-1)(-2)=4-2n+2=6-2n.$$\n\n【確認】  \n$n=1$ のとき $a_1=6-2=4$（初項と一致）。  \n$n\\to n+1$ として  \n$$a_{n+1}=6-2(n+1)=6-2n-2=(6-2n)-2=a_n-2,$$  \n漸化式も満たすので正しい。\n\nしたがって、求める一般項は  \n\n$$a_n=6-2n \\qquad(n\\ge1).$$",
            "is_correct": true
        },
        {
            "statement": "次の条件によって定められる数列 $\\{a_n\\}$ の一般項を求めよ。 $$ a_1 = 2, \\quad a_{n+1} = 5a_n $$",
            "solution": "$$ a_n = 2 \\cdot 5^{n-1} $$",
            "gpt": "【解法】\n\n与えられた数列 $\\{a_n\\}$ は\n\n$ a_1 = 2,\\qquad a_{n+1}=5a_n\\quad(n=1,2,3,\\dots)$\n\nで定義されている。\n\n1. まず $a_2$ を求めると  \n   $a_2 = 5a_1 = 5\\cdot2 = 10$  \n   同様に  \n   $a_3 = 5a_2 = 5\\cdot10 = 50$  \n   $a_4 = 5a_3 = 5\\cdot50 = 250$  \n   …と続き、各項は前項の $5$ 倍になっている。\n\n2. このような数列は公比 $5$ の等比数列であると考えられるので、一般項を  \n   $a_n = 2\\cdot5^{n-1}$  \n   と推測できる。\n\n3. 以上を数学的帰納法で確認する。\n\n   (1) $n=1$ のとき  \n   $a_1 = 2 = 2\\cdot5^{1-1}$  \n   で成り立つ。\n\n   (2) $n=k$ のとき $a_k = 2\\cdot5^{k-1}$ が成り立つと仮定する。\n\n   (3) $n=k+1$ のとき  \n   $a_{k+1}=5a_k = 5\\left(2\\cdot5^{k-1}\\right)=2\\cdot5^k = 2\\cdot5^{(k+1)-1}$  \n   となり、帰納法の仮定を満たす。\n\n   よってすべての正の整数 $n$ で  \n   $a_n = 2\\cdot5^{n-1}$  \n   が成り立つ。\n\n【結論】\n\n数列 $\\{a_n\\}$ の一般項は\n\n$a_n = 2\\cdot5^{\\,n-1}\\quad(n=1,2,3,\\dots)$\n\nである。",
            "is_correct": true
        },
        {
            "statement": "次の条件によって定められる数列 $\\{a_n\\}$ の一般項を求めよ。 $$ a_1 = 5, \\quad a_{n+1} = -3a_n $$",
            "solution": "$$ a_n = 5(-3)^{n-1} $$",
            "gpt": "【解答】\n\nまず、与えられた数列 $\\{a_n\\}$ は  \n$a_1=5,\\; a_{n+1}=-3a_n\\;(n=1,2,3,\\dots)$  \nという漸化式で定められています。\n\nⅠ. 数列の形を調べる  \n漸化式から、各項は直前の項に $-3$ を掛けて得られていることがわかります。すなわち\n\n$a_2=-3a_1,\\; a_3=-3a_2,\\; a_4=-3a_3,\\ \\dots$\n\nよって  \n\n$a_2=5(-3),\\; a_3=5(-3)^2,\\; a_4=5(-3)^3,\\dots$  \n\nと続き、一般に  \n\n$a_n=5(-3)^{n-1}$  \n\nであろうと予想できます。\n\nⅡ. 数学的帰納法による確認  \n(1) $n=1$ のとき  \n右辺 $5(-3)^{1-1}=5(-3)^0=5$ は条件の $a_1=5$ と一致する。  \n\n(2) $n=k$ のとき成り立つと仮定  \n$a_k=5(-3)^{k-1}$  \n\n(3) $n=k+1$ について示す  \n漸化式より $a_{k+1}=-3a_k$。  \n仮定を代入すると  \n$a_{k+1}=-3\\{5(-3)^{k-1}\\}=5(-3)^k$  \nこれは求める形 $5(-3)^{(k+1)-1}$ と一致する。\n\n(4) ①②③より、数学的帰納法によってすべての自然数 $n$ で  \n$a_n=5(-3)^{n-1}$ が成り立つ。\n\nⅢ. 結論  \n一般項は  \n\n$$a_n=5(-3)^{n-1}\\quad(n=1,2,3,\\dots)$$\n\nこれ以外の形は漸化式と初期条件を同時に満たさないため、これが唯一の解である。",
            "is_correct": true
        },
        {
            "statement": "次の条件によって定められる数列 $\\{a_n\\}$ の一般項を求めよ。 $$ a_1 = 1, \\quad a_{n+1} - a_n = 2n $$",
            "solution": "$$ a_n = n^2 - n + 1 $$",
            "gpt": "【解答】\n\n与えられた数列 $\\{a_n\\}$ は  \n\n$$a_1 = 1,\\qquad a_{n+1}-a_n = 2n\\quad (n=1,2,3,\\dots)$$  \n\nで定められている。以下、この漸化式から一般項 $a_n$ を求める。\n\n──────────────────────────  \n1. 階差を累積して和をとる  \n──────────────────────────  \n\n$n\\ge1$ に対して\n\n$$a_{n+1}=a_1+\\sum_{k=1}^{n}(a_{k+1}-a_k)$$\n\nが成り立つ（初項から順に差を足し合わせれば $a_{n+1}$ になる）。  \nここで $a_{k+1}-a_k=2k$ なので\n\n$$a_{n+1}=a_1+\\sum_{k=1}^{n}2k = 1 + 2\\sum_{k=1}^{n}k.$$\n\n高校数学の公式 $\\sum_{k=1}^{n}k=\\dfrac{n(n+1)}{2}$ を用いると\n\n$$a_{n+1}=1+2\\cdot\\frac{n(n+1)}{2}=1+n(n+1).$$\n\nしたがって\n\n$$a_{n+1}=n^2+n+1.$$\n\nここで $n$ を $n-1$ に置き換えれば\n\n$$a_n=(n-1)^2+(n-1)+1=n^2-n+1\\qquad(n\\ge1).$$\n\n──────────────────────────  \n2. 数学的帰納法による確認（任意の $n$ で成立）  \n──────────────────────────  \n\n(1) $n=1$ のとき  \n$$a_1 = 1^2-1+1 = 1$$  \nで成り立つ。\n\n(2) 任意の正整数 $n$ で $a_n=n^2-n+1$ と仮定すると\n\n$$a_{n+1}=a_n+2n=(n^2-n+1)+2n=n^2+n+1=(n+1)^2-(n+1)+1.$$\n\n従って $n+1$ に対しても成立する。  \n(1)(2)より数学的帰納法によりすべての正整数 $n$ で\n\n$$a_n=n^2-n+1$$\n\nが成り立つことが証明された。\n\n──────────────────────────  \n【結論】  \n\n数列 $\\{a_n\\}$ の一般項は  \n\n$$\\boxed{\\,a_n = n^2 - n + 1\\,(n=1,2,3,\\dots)\\,}.$$",
            "is_correct": true
        },
        {
            "statement": "次の条件によって定められる数列 $\\{a_n\\}$ の一般項を求めよ。 $$ a_1 = 2, \\quad a_{n+1} - a_n = 3n^2 + n $$",
            "solution": "$$ a_n = n^3 - n^2 + 2 $$",
            "gpt": "解答\n\n(1) 累積和をとって一般項を作る  \n漸化式  \n$$a_{n+1}-a_n = 3n^2+n \\qquad(n\\ge1)$$  \nは右辺が $n$ だけの式なので、両辺を $1$ から $n-1$ まで足し合わせる。\n\n$$\\sum_{k=1}^{\\,n-1}(a_{k+1}-a_k)=\\sum_{k=1}^{\\,n-1}(3k^2+k)$$\n\n左辺は望ましい望む telescoping（差分の相殺）で\n\n$$\\sum_{k=1}^{\\,n-1}(a_{k+1}-a_k)=a_n-a_1.$$\n\nよって\n\n$$a_n-a_1=\\sum_{k=1}^{\\,n-1}(3k^2+k).$$\n\n(2) 右辺の和を計算する  \n$$\\sum_{k=1}^{\\,n-1}(3k^2+k)=3\\sum_{k=1}^{\\,n-1}k^2+\\sum_{k=1}^{\\,n-1}k.$$\n\n既知の公式\n\n$\\displaystyle\\sum_{k=1}^{m}k=\\frac{m(m+1)}{2},\\qquad\n\\displaystyle\\sum_{k=1}^{m}k^2=\\frac{m(m+1)(2m+1)}{6}$\n\nを $m=n-1$ として用いる。\n\n(i) 二乗の和  \n$$3\\sum_{k=1}^{\\,n-1}k^2=3\\cdot\\frac{(n-1)n(2n-1)}{6}\n                       =\\frac{(n-1)n(2n-1)}{2}.$$\n\n(ii) １次の和  \n$$\\sum_{k=1}^{\\,n-1}k=\\frac{(n-1)n}{2}.$$\n\n両者を合わせると\n\n$$\\sum_{k=1}^{\\,n-1}(3k^2+k)\n   =\\frac{(n-1)n(2n-1)}{2}+\\frac{(n-1)n}{2}\n   =\\frac{(n-1)n\\bigl[(2n-1)+1\\bigr]}{2}\n   =\\frac{(n-1)n\\cdot(2n)}{2}\n   =n^2(n-1).$$\n\n(3) 一般項の決定  \n$$a_n-a_1=n^2(n-1)\\quad\\Longrightarrow\\quad\n  a_n= a_1 + n^2(n-1).$$\n\n初項 $a_1=2$ を代入すれば\n\n$$a_n = 2 + n^2(n-1).$$\n\n(4) 確認  \n$$a_{n+1}-a_n=\\bigl[2+(n+1)^2n\\bigr]-\\bigl[2+n^2(n-1)\\bigr]\n            =n(n+1)^2-n^2(n-1)\n            =3n^2+n,$$\n漸化式を満たすことが確かめられる。\n\nしたがって求める一般項は\n\n$$\\boxed{\\,a_n = 2 + n^2(n-1)\\,}\\qquad(n\\ge1).$$",
            "is_correct": true
        },
        {
            "statement": "次の条件によって定められる数列 $\\{a_n\\}$ の一般項を求めよ。 $$ a_1 = 1, \\quad a_{n+1} = a_n + n^2 $$",
            "solution": "$$ a_n = \\frac{1}{6}( 2n^3 - 3n^2 + n + 6 ) $$",
            "gpt": "【解答】\n\n数列 $\\{a_n\\}$ は\n\n$$a_1 = 1,\\qquad a_{n+1}=a_n+n^2\\qquad(n\\ge1)$$\n\nで定められています。  \n一般項 $a_n$ を求めるには、漸化式を「差分」の形で利用して和をとるのが基本的な手順です。\n\n────────────────────\n1. 漸化式を望ましい形に書く  \n────────────────────\n$$a_{n+1}-a_n = n^2\\qquad(n\\ge1)$$  \nこの両辺を $n=1,2,\\dots ,n-1$ まで足し合わせてみます。\n\n────────────────────\n2. 望ましい区間で和をとる（テレスコーピング）  \n────────────────────\n左辺は「隣り合う項の差」の和なので望ましく「つるつる」消えます（テレスコーピング）。\n\n左辺：  \n\\[\n\\sum_{k=1}^{\\,n-1}(a_{k+1}-a_k)=a_n-a_1\n\\]\n\n右辺：  \n\\[\n\\sum_{k=1}^{\\,n-1}k^2\n\\]\n\nしたがって\n\n$$a_n-a_1=\\sum_{k=1}^{\\,n-1}k^2.$$\n\n初項 $a_1=1$ を代入すると\n\n$$a_n = 1+\\sum_{k=1}^{\\,n-1}k^2.\\tag{★}$$\n\n────────────────────\n3. 二乗数列の和公式を利用  \n────────────────────\n高校数学で学ぶ公式\n\n$$\\sum_{k=1}^{m}k^2=\\frac{m(m+1)(2m+1)}{6}$$\n\nを $m=n-1$ として用います。\n\n\\[\n\\sum_{k=1}^{\\,n-1}k^2\n=\\frac{(n-1)n(2n-1)}{6}.\n\\]\n\nこれを (★) に入れると\n\n$$a_n = 1 + \\frac{(n-1)n(2n-1)}{6}.$$\n\n────────────────────\n4. 必要なら多項式の形に整理  \n────────────────────\n\\[\n\\frac{(n-1)n(2n-1)}{6}\n=\\frac{(n^2-n)(2n-1)}{6}\n=\\frac{2n^3-3n^2+n}{6},\n\\]\n\nよって\n\n$$a_n=\\frac{2n^3-3n^2+n}{6}+1=\\frac{2n^3-3n^2+n+6}{6}.$$\n\nどちらの形でも正解ですが、通常は\n\n$$\\boxed{\\,a_n = 1 + \\dfrac{(n-1)n(2n-1)}{6}\\,}\\qquad(n\\ge1)$$\n\nとまとめるのが見やすいでしょう。\n\n────────────────────\n5. （確認）$n=1$ のとき  \n────────────────────\n\\[\na_1 = 1 + \\frac{(1-1)\\cdot1\\cdot(2\\cdot1-1)}{6}=1+0=1,\n\\]\n初期条件も満たしていますから、上式はすべての自然数 $n$ について成立します。",
            "is_correct": true
        },
        {
            "statement": "次の条件によって定められる数列 $\\{a_n\\}$ の一般項を求めよ。 $$ a_1 = 1, \\quad a_{n+1} = a_n + 4^n $$",
            "solution": "$$ a_n = \\frac{1}{3}( 4^n - 1 ) $$",
            "gpt": "【解答】\n\n(1) まずは漸化式を整理する  \n与えられた数列 $\\{a_n\\}$ は  \n$$a_{n+1}-a_n = 4^n \\quad (n\\ge 1)$$  \nという「隣接２項の差」が決まっている型です。  \n\n(2) 階差をすべて足し上げて $a_n$ を求める  \n$n\\,( \\ge 2)$ まで式を並べると  \n\n\\[\n\\begin{aligned}\na_2-a_1 &= 4^1,\\\\\na_3-a_2 &= 4^2,\\\\\na_4-a_3 &= 4^3,\\\\\n&\\ \\vdots\\\\\na_n-a_{n-1} &= 4^{\\,n-1}.\n\\end{aligned}\n\\]\n\n左辺をすべて足すと望む $a_n-a_1$、右辺は等比数列の和になります。  \n\n\\[\na_n-a_1=\\sum_{k=1}^{n-1}4^k.\n\\]\n\n初項 $a_1=1$ を代入し、右辺を計算する。等比数列の和公式  \n$\\sum_{k=1}^{n-1}r^k=\\dfrac{r(r^{\\,n-1}-1)}{r-1}$ を $r=4$ に当てはめると  \n\n\\[\n\\sum_{k=1}^{n-1}4^k=\\frac{4(4^{\\,n-1}-1)}{4-1}\n                 =\\frac{4^{\\,n}-4}{3}.\n\\]\n\nよって  \n\n\\[\na_n\n= a_1+\\frac{4^{\\,n}-4}{3}\n= 1+\\frac{4^{\\,n}-4}{3}\n= \\frac{4^{\\,n}-1}{3}.\n\\]\n\n(3) 結論  \n一般項は  \n\n$$a_n=\\frac{4^{\\,n}-1}{3}\\quad(n\\ge 1).$$  \n\n(4)（確認）$n=1$ について  \n$$a_1=\\frac{4^{\\,1}-1}{3}=1$$  \nで与えられた初項と一致するため、式はすべての $n\\in\\mathbb{N}$ で成り立ちます。",
            "is_correct": true
        },
        {
            "statement": "次の条件によって定められる数列 $\\{a_n\\}$ の一般項を求めよ。 $$ a_1 = 2, \\quad a_{n+1} = 3a_n - 2 $$",
            "solution": "$$ a_n = 3^{n-1} + 1 $$",
            "gpt": "【解答】\n\n(1) 差分方程式の形を整える  \n与えられた漸化式は\n\n$$a_{n+1}=3a_n-2 \\quad(n\\ge1)$$\n\nで、右辺に定数項がある一次線形漸化式です。  \nこのタイプは「定数分だけずらす」ことで等比型に帰着できます。\n\n(2) 定数分だけずらして等比型に変換  \n未知の定数 $\\alpha$ を用いて\n\n$$a_{n+1}-\\alpha = 3\\bigl(a_n-\\alpha\\bigr)$$\n\nとなる $\\alpha$ を探します。  \n左辺を展開し、元の漸化式 $a_{n+1}=3a_n-2$ を代入すると\n\n$$3a_n-2-\\alpha = 3a_n-3\\alpha.$$\n\n両辺から $3a_n$ を除くと\n\n$$-2-\\alpha = -3\\alpha \\quad\\Longrightarrow\\quad -2 = -2\\alpha \\quad\\Longrightarrow\\quad \\alpha = 1.$$\n\nしたがって\n\n$$a_{n+1}-1 = 3\\bigl(a_n-1\\bigr).$$\n\nここで\n\n$$b_n := a_n-1$$\n\nと置くと\n\n$$b_{n+1}=3\\,b_n \\quad(n\\ge1).$$\n\n(3) 等比数列 $b_n$ を解く  \n初項は $b_1 = a_1-1 = 2-1 = 1$。  \n公比 $3$ の等比数列なので\n\n$$b_n = 1\\cdot 3^{\\,n-1}=3^{\\,n-1}.$$\n\n(4) 元の数列 $a_n$ を求める  \n$b_n=a_n-1$ だったので\n\n$$a_n = b_n + 1 = 3^{\\,n-1}+1.$$\n\n(5) 確認  \n$n=1$ のとき $a_1 = 3^{0}+1 = 2$ で初期条件を満たす。  \nまた\n\n$$a_{n+1}=3^{\\,n}+1, \\quad 3a_n-2 = 3\\bigl(3^{\\,n-1}+1\\bigr)-2 \n= 3^{\\,n}+3-2 = 3^{\\,n}+1,$$\n\nなので漸化式も成立する。\n\nよって、求める一般項は\n\n$$\\boxed{a_n = 3^{\\,n-1}+1 \\quad(n\\ge1)}.$$",
            "is_correct": true
        },
        {
            "statement": "次の条件によって定められる数列 $\\{a_n\\}$ の一般項を求めよ。 $$ a_1 = 1, \\quad a_{n+1} = \\frac{1}{3}a_n + 2 $$",
            "solution": "$$ a_n = -2 ( \\frac{1}{3} )^{n-1} + 3 $$",
            "gpt": "【解答】\n\n1. 漸化式の整理  \n　与えられた漸化式は  \n　$$a_{n+1}= \\frac13 a_n + 2 \\qquad(n=1,2,3,\\dots)$$  \n　です。これは「一次同次＋定数項」の形をもつ一次漸化式なので，  \n　(1) 同次部分を解く  \n　(2) 定数項による特解を求める  \n　(3) 初期条件で定数を決定する  \n　という手順で一般項を求めます。\n\n2. 同次方程式（定数項を 0 にしたもの）の解  \n　定数項を取り除くと  \n　$$b_{n+1}= \\frac13 b_n$$  \n　となります。これは公比 $\\frac13$ の等比数列なので  \n　$$b_n = b_1\\!\\left(\\frac13\\right)^{n-1} \\qquad(\\text{一般解})$$  \n　と書けます。\n\n3. 定数係数の特解  \n　右辺の定数 $2$ に対応する特解を「数列がやがて一定値 $A$ に落ち着く」と仮定して探します。  \n　数列が一定になるとき $a_{n+1}=a_n=A$ と置けるので  \n　$$A = \\frac13 A + 2$$  \n　$$\\frac23 A = 2 \\quad\\Longrightarrow\\quad A = 3$$  \n　ゆえに「すべての $n$ で $a_n=3$」という数列が特解になります。\n\n4. 一般解  \n　漸化式は線形なので  \n　$$a_n = (\\text{同次解}) + (\\text{特解})$$  \n　$$a_n = b_n + 3 = b_1\\!\\left(\\frac13\\right)^{n-1} + 3$$  \n　となります。\n\n5. 初期条件で定数決定  \n　初期条件 $a_1=1$ を代入すると  \n　$$1 = b_1\\!\\left(\\frac13\\right)^{0} + 3 = b_1 + 3$$  \n　$$b_1 = -2$$  \n　したがって  \n　$$a_n = -2\\left(\\frac13\\right)^{n-1} + 3$$  \n\n6. まとめ（一般項）  \n　$$\\boxed{\\,a_n = 3 - 2\\left(\\frac13\\right)^{n-1}\\,}$$  \n　あるいは指数を正にそろえて  \n　$$a_n = 3 - 2\\cdot 3^{1-n}$$  \n　と表しても同じ意味です。\n\n(参考) 挙動の確認  \n$n\\to\\infty$ とすると $\\left(\\frac13\\right)^{n-1}\\to0$ なので  \n$$\\lim_{n\\to\\infty} a_n = 3.$$  \n実際に最初の数項を計算すると  \n$a_1=1,\\; a_2=\\frac13\\cdot1+2=\\frac73,\\; a_3=\\frac13\\cdot\\frac73+2=\\frac{25}{9},\\dots$  \nと 3 に近づいていく様子がわかります。",
            "is_correct": true
        },
        {
            "statement": "次の条件によって定められる数列 $\\{a_n\\}$ の一般項を求めよ。 $$ a_1 = 1, \\quad a_{n+1} = 9 - 2a_n $$",
            "solution": "$$ a_n = (-2)^n + 3 $$",
            "gpt": "【解答】\n\n(1) まずは様子を見る  \n初項と数項を計算してみると  \n$a_1 = 1$，  \n$a_2 = 9 - 2a_1 = 9 - 2 = 7$，  \n$a_3 = 9 - 2a_2 = 9 - 14 = -5$，  \n$a_4 = 9 - 2a_3 = 9 - (-10) = 19$ …  \nとなり，$1,\\,7,\\,-5,\\,19,\\dots$ と大きく振動していることがわかります。\n\n(2) 定点（不動点）を探す  \n一次漸化式  \n$a_{n+1} = 9 - 2a_n$  \nでは，「次も同じ値になる」定点 $p$ を考えると  \n$p = 9 - 2p\\ \\Longrightarrow\\ 3p = 9\\ \\Longrightarrow\\ p = 3$  \nとなります。  \nこの $p=3$ を基準にずれを取ると式が単純化します。\n\n(3) ずれを取って等比型に帰着  \n$b_n = a_n - 3$ とおくと  \n$b_{n+1} = a_{n+1} - 3 = (9 - 2a_n) - 3 = 6 - 2a_n  \n= 6 - 2(b_n + 3) = 6 - 2b_n - 6 = -2\\,b_n$  \nよって  \n$$b_{n+1} = -2\\,b_n$$  \nとなり，これは初等的な等比数列である。\n\n(4) $b_n$ の一般項  \n初項は $b_1 = a_1 - 3 = 1 - 3 = -2$。  \n公比は $-2$ なので  \n$$b_n = (-2)^{\\,n-1} b_1 = (-2)^{\\,n-1}(-2) = (-2)^{\\,n}$$\n\n(5) 元に戻して $a_n$ の一般項  \n$$a_n = 3 + b_n = 3 + (-2)^{\\,n}$$\n\n(6) 確認  \n$n=1$ のとき $a_1 = 3 + (-2)^1 = 3-2 = 1$（与えられた初項と一致）  \n漸化式への代入でも  \n$a_{n+1}=3+(-2)^{n+1},\\ a_n=3+(-2)^n$ とすると  \n$9-2a_n = 9-2\\{3+(-2)^n\\}=9-6-2(-2)^n=3+(-2)^{n+1}=a_{n+1}$  \nが成り立つので正しい。\n\n(7) 結論  \n数列 $\\{a_n\\}$ の一般項は  \n$$a_n = 3 + (-2)^{\\,n}\\quad(n=1,2,3,\\dots)$$",
            "is_correct": true
        },
        {
            "statement": "次の条件によって定められる数列 $\\{a_n\\}$ の一般項を求めよ。 $$ a_1 = 1, \\quad a_{n+1} = 4a_n + 3 $$",
            "solution": "$$ a_n = 2 \\cdot 4^{n-1} - 1 $$",
            "gpt": "【解答】\n\n本数列は一次不定係数型の漸化式\n$$a_{n+1}=4a_n+3\\quad(n\\ge1),\\qquad a_1=1$$\nで与えられています。  \n一次漸化式\n$$u_{n+1}=pu_n+q$$\nの一般解は\n\n1. 同次部分 $u_{n+1}=pu_n$ の解 $C\\,p^{\\,n}$（$C$ は定数）\n2. 定数解（特解）を 1 つとって $u_n=k$\n\nを重ね合わせた形で表せることを利用して求めます。\n\n────────────────────────\n1. 同次部分の解  \n$$a_{n+1}^{(h)}=4a_n^{(h)}\\quad\\Longrightarrow\\quad a_n^{(h)}=C\\,4^{\\,n}$$\n（ただし $C$ は定数）\n\n2. 特解の決定  \n定数解 $a_n=k$ と仮定すると\n$$k=4k+3\\quad\\Longrightarrow\\quad3k=-3\\quad\\Longrightarrow\\quad k=-1$$\n\n3. 一般解  \n$$a_n=C\\,4^{\\,n}-1$$\n\n4. 初期条件で定数 $C$ を決める  \n$$a_1=1 \\Longrightarrow 1=C\\,4^1-1\\quad\\Longrightarrow\\quad C=2$$\n\n────────────────────────\nよって一般項は\n$$a_n=2\\cdot4^{\\,n-1}-1$$\nあるいは指数を 2 の冪でまとめて\n$$a_n=2^{\\,2n-1}-1$$\nとも書けます。\n\n【確認】  \n漸化式に代入してみると\n\\[\na_{n+1}=2\\cdot4^{\\,n}-1,\\qquad\n4a_n+3=4\\bigl(2\\cdot4^{\\,n-1}-1\\bigr)+3=2\\cdot4^{\\,n}-1\n\\]\nで一致するので正しいことが確かめられます。",
            "is_correct": true
        },
        {
            "statement": "次の条件によって定められる数列 $\\{a_n\\}$ の一般項を求めよ。 $$ a_1 = 1, \\quad a_{n+1} = -2a_n + 1 $$",
            "solution": "$$ a_n = \\frac{ 1 - (-2)^n }{ 3 } $$",
            "gpt": "【解答】\n\n数列 $\\{a_n\\}$ は  \n$a_1 = 1,\\quad a_{n+1}= -2a_n + 1$（$n=1,2,3,\\dots$）  \nで定まっています。一次の線形漸化式なので，  \n「（１）定数解（特解）を探す　→　（２）同次方程式の解を足す」  \nという標準手順で一般項を求めます。\n\n────────────────────\n１．定数解（特解）を求める  \n$a_n$ が定数 $k$ であると仮定すると\n\n$k = -2k + 1 \\quad\\Longrightarrow\\quad 3k = 1 \\quad\\Longrightarrow\\quad k = \\dfrac13$.\n\nしたがって特解は  \n$a_n^{(p)} = \\dfrac13$.\n\n────────────────────\n２．同次方程式の解を求める  \n特解を差し引いた差\n\n$b_n = a_n - \\dfrac13$\n\nを考えると\n\n$b_{n+1} = a_{n+1} - \\dfrac13 = \\bigl(-2a_n + 1\\bigr) - \\dfrac13\n        = -2\\Bigl(a_n - \\dfrac13\\Bigr)\n        = -2\\,b_n$.\n\nよって同次漸化式\n\n$b_{n+1} = -2\\,b_n$\n\nを得る。初項は\n\n$b_1 = a_1 - \\dfrac13 = 1 - \\dfrac13 = \\dfrac23$.\n\n一般解は\n\n$b_n = b_1(-2)^{\\,n-1} = \\dfrac23\\,(-2)^{\\,n-1}$.\n\n────────────────────\n３．元の数列に戻す  \n$a_n = b_n + \\dfrac13$ なので\n\n$a_n = \\dfrac23\\,(-2)^{\\,n-1} + \\dfrac13$.\n\n整理すると\n\n$a_n = \\dfrac13\\!\\left\\{\\,1 + 2(-2)^{\\,n-1}\\right\\}$.\n\n────────────────────\n４．確認（任意）  \n$n=1$ のとき  \n$a_1 = \\dfrac13\\!\\bigl\\{1 + 2(-2)^{0}\\bigr\\} = \\dfrac13(1+2)=1$ で条件を満たす。  \n\n漸化式チェック：  \nもし $a_n = \\dfrac13 + \\dfrac23(-2)^{n-1}$ なら\n\n$a_{n+1} = \\dfrac13 + \\dfrac23(-2)^{n}\n          = -2\\!\\left(\\dfrac13 + \\dfrac23(-2)^{n-1}\\right) + 1\n          = -2a_n + 1$\n\nが成立する。よって一般項は正しい。\n\n────────────────────\n【結論】\n\n$a_n = \\dfrac13 + \\dfrac23\\,(-2)^{\\,n-1}\\quad(n=1,2,3,\\dots)$\n\n（あるいは $a_n = \\dfrac13\\{1 + 2(-2)^{\\,n-1}\\}$）",
            "is_correct": true
        },
        {
            "statement": "次の条件によって定められる数列 $\\{a_n\\}$ の一般項を求めよ。 $$ a_1 = 0, \\quad 2a_{n+1} - 3a_n = 1 $$",
            "solution": "$$ a_n = ( \\frac{3}{2} )^{n-1} - 1 $$",
            "gpt": "【解答】\n\n数列 $\\{a_n\\}$ は  \n$$2a_{n+1}-3a_n = 1 \\qquad(n=1,2,3,\\dots)$$  \nによって定められ、初項は $a_1=0$ である。一次漸化式（線形漸化式）の典型的な解き方に従って一般項を求める。\n\n────────────────────────\n1．同次方程式の解を求める  \n右辺を 0 とした同次方程式  \n$$2a_{n+1}-3a_n = 0$$  \nをまず解く。両辺を 2 で割れば  \n$$a_{n+1}=\\frac32\\,a_n.$$\n\nこれは公比 $\\dfrac32$ の等比数列であるから  \n$$a_n^{(h)} = C\\left(\\frac32\\right)^{\\,n-1} \\qquad(C は定数)$$  \nが同次方程式の一般解である。\n\n────────────────────────\n2．特解を 1 つ求める  \n与えられた漸化式の右辺は定数 1 なので、定数解 $a_n=A$（$n$ に依存しない値）を仮定する。これを元の漸化式に代入すると  \n$$2A-3A = 1 \\quad\\Longrightarrow\\quad -A = 1 \\quad\\Longrightarrow\\quad A = -1.$$\n\nよって特解の一例は  \n$$a_n^{(p)} = -1.$$\n\n────────────────────────\n3．一般解と初期条件の適用  \n線形漸化式の一般解は「同次解＋特解」の形になるから  \n$$a_n = a_n^{(h)} + a_n^{(p)} = C\\left(\\frac32\\right)^{\\,n-1} - 1.$$\n\n初期条件 $a_1 = 0$ を代入して $C$ を決定する。$n=1$ を入れると  \n$$0 = C\\left(\\frac32\\right)^{\\,1-1} - 1 = C - 1 \\quad\\Longrightarrow\\quad C = 1.$$\n\n────────────────────────\n4．結論  \n$$a_n = \\left(\\frac32\\right)^{\\,n-1} - 1 \\qquad(n=1,2,3,\\dots)$$\n\n────────────────────────\n5．確認  \n漸化式を満たすかどうかをチェックする。  \n左辺：$2a_{n+1}-3a_n$  \n$$= 2\\!\\left[\\left(\\frac32\\right)^{\\,n}-1\\right] - 3\\!\\left[\\left(\\frac32\\right)^{\\,n-1}-1\\right]\n= 2\\left(\\frac32\\right)^{\\,n} -2 -3\\left(\\frac32\\right)^{\\,n-1}+3.$$\n右辺は  \n$$2\\left(\\frac32\\right)^{\\,n} - 3\\left(\\frac32\\right)^{\\,n-1} = 0,$$  \nなので残りは $-2+3=1$．よって漸化式 $2a_{n+1}-3a_n=1$ が確かに成り立つ。\n\n従って求める一般項は上記で確定である。",
            "is_correct": true
        },
        {
            "statement": "次の条件によって定められる数列 $\\{a_n\\}$ の一般項を求めよ。 $$ a_1 = 1, \\quad a_{n+1} = \\frac{ 3a_n }{ a_n + 3 } $$",
            "solution": "$$ a_n = \\frac{ 3 }{ n + 2 } $$",
            "gpt": "【解答】\n\nまず与えられた漸化式  \n$$a_{n+1}=\\frac{3a_n}{a_n+3}\\qquad(n=1,2,\\dots)$$  \nを変形して扱いやすい形にします。\n\n1. 逆数をとる  \n右辺の分母に $a_n$ が入っているので，両辺の逆数をとってみます。  \n$$\\frac1{a_{n+1}}=\\frac{a_n+3}{3a_n}=\\frac13\\left(1+\\frac3{a_n}\\right)=\\frac13+\\frac1{a_n}$$\n\n2. 新しい数列 $b_n$ の導入  \n$$b_n=\\frac1{a_n}$$  \nと置くと\n$$b_{n+1}=b_n+\\frac13$$\nとなり，これは公差 $\\dfrac13$ の等差数列です。\n\n3. $b_n$ の一般項  \n初項は $b_1=\\dfrac1{a_1}=1$ なので\n$$b_n = b_1 + (n-1)\\cdot\\frac13 = 1+\\frac{n-1}3=\\frac{n+2}3$$\n\n4. 元の数列 $a_n$ に戻す  \n$$a_n=\\frac1{b_n}= \\frac1{\\dfrac{n+2}3}= \\frac3{\\,n+2\\,}$$\n\n5. 確認（数学的帰納法でも確認可能）  \n$n=1$ で $a_1=\\dfrac3{1+2}=1$ なので初期条件を満たす。  \n漸化式への代入も\n$$a_{n+1}= \\frac3{(n+1)+2}= \\frac3{n+3},\\qquad\n\\frac{3a_n}{a_n+3}= \\frac{3\\cdot\\dfrac3{n+2}}{\\dfrac3{n+2}+3}\n= \\frac{\\dfrac9{n+2}}{\\dfrac{3+n+2}{n+2}}\n= \\frac9{n+3}\\cdot\\frac1{3}\n= \\frac3{n+3}$$\nで一致するため正しい。\n\nよって、数列 $\\{a_n\\}$ の一般項は  \n\n$$\\boxed{\\,a_n=\\dfrac{3}{n+2}\\;}\\quad(n=1,2,\\dots)$$",
            "is_correct": true
        },
        {
            "statement": "次の条件によって定められる数列 $\\{a_n\\}$ の一般項を求めよ。 $$ a_1 = 1, \\quad a_{n+1} = \\frac{ a_n }{ a_n + 1 } $$",
            "solution": "$$ a_n = \\frac{1}{n} $$",
            "gpt": "【解説】\n\n数列 $\\{a_n\\}$ は  \n$$a_1 = 1, \\qquad a_{n+1} = \\frac{a_n}{a_n+1}\\qquad(n=1,2,\\dots)$$  \nで定められています。一般項 $a_n$ を求めましょう。\n\n────────────────────\n1．逆数をとってみる  \n────────────────────  \n漸化式の分母・分子に $a_n$ が現れているので、逆数をとると形が単純になると予想できます。  \n$$b_n=\\frac1{a_n}\\quad\\Longrightarrow\\quad a_n=\\frac1{b_n}$$\nとおくと，漸化式は  \n\n\\[\n\\frac{1}{b_{n+1}}\n      =\\frac{\\dfrac1{b_n}}{\\dfrac1{b_n}+1}\n      =\\frac{\\dfrac1{b_n}}{\\dfrac{1+b_n}{b_n}}\n      =\\frac1{1+b_n}\n\\]\n\nしたがって  \n\n\\[\nb_{n+1}=1+b_n.\n\\]\n\n────────────────────  \n2．一次漸化式の解  \n────────────────────  \nこれは差が一定 $1$ の等差数列です。初項は  \n\n\\[\nb_1=\\frac1{a_1}=\\frac11=1.\n\\]\n\nゆえに  \n\n\\[\nb_n=b_1+(n-1)\\times1=1+(n-1)=n.\n\\]\n\n────────────────────  \n3．元の数列に戻す  \n────────────────────  \n$$a_n=\\frac1{b_n}=\\frac1n\\quad(n=1,2,\\dots)$$\n\n────────────────────  \n4．確認  \n────────────────────  \n帰納的に確認すると  \n\\[\na_{n+1}=\\frac{a_n}{a_n+1}=\\frac{\\dfrac1n}{\\dfrac1n+1}\n      =\\frac{\\dfrac1n}{\\dfrac{1+n}{n}}\n      =\\frac1{n+1},\n\\]\n確かに求めた式を満たします。\n\n────────────────────  \n【結論】  \n$$\\boxed{\\,a_n=\\dfrac1n\\,(n=1,2,\\dots)\\,}$$",
            "is_correct": true
        },
        {
            "statement": "次の条件によって定められる数列 $\\{a_n\\}$ の一般項を求めよ。 $$ a_1 = \\frac{1}{2}, \\quad a_{n+1} = \\frac{ a_n }{ 2a_n + 3 } $$",
            "solution": "$$ a_n =  \\frac{ 1 }{ 3^n - 1 } $$",
            "gpt": "【解答】\n\nはじめに漸化式を書き直しておく。  \n与えられた数列 $\\{a_n\\}$ は\n\n$$a_1=\\frac12,\\qquad a_{n+1}= \\frac{a_n}{\\,2a_n+3\\,}\\qquad(n=1,2,3,\\dots)$$\n\nで定まる。一般項 $a_n$ を求める。\n\n────────────────\n1　逆数を取って一次漸化式に帰着させる  \n────────────────\n\n右辺に $a_n$ が分母にも分子にも現れるため、そのままでは扱いにくい。  \nそこで逆数\n\n$$b_n=\\frac1{a_n}$$\n\nを導入する。\n\n$a_{n+1}$ の定義式を逆数に直すと\n\n\\[\nb_{n+1}=\\frac1{a_{n+1}}\n       =\\frac{2a_n+3}{a_n}\n       =2+\\frac3{a_n}\n       =2+3\\,b_n.\n\\]\n\nすなわち\n\n$$b_{n+1}=3b_n+2 \\qquad(n\\ge1),\\qquad b_1=\\frac1{a_1}=2.$$\n\nこれは一次不完全（線形一次非同次）漸化式で、高校数学 II で学ぶ典型的な形である。\n\n────────────────\n2　一次不完全漸化式 $b_{n+1}=3b_n+2$ を解く  \n────────────────\n\n(i) 同次方程式部分  \n$b_{n+1}=3b_n$ の解は $b_n^{(h)}=C\\cdot3^{\\,n-1}$。\n\n(ii) 定数特解  \n定数 $b_n^{(p)}=k$ と置くと  \n$k=3k+2 \\;\\Longrightarrow\\; -2k=2 \\;\\Longrightarrow\\; k=-1$。\n\n(iii) 一般解  \n$$b_n=b_n^{(h)}+b_n^{(p)}=C\\cdot3^{\\,n-1}-1.$$\n\n初期条件 $b_1=2$ を代入すると\n\n$$2=C\\cdot3^{\\,0}-1=C-1\\quad\\Longrightarrow\\quad C=3.$$\n\nしたがって\n\n$$b_n=3\\cdot3^{\\,n-1}-1=3^{\\,n}-1.$$\n\n────────────────\n3　元の数列 $a_n$ の一般項  \n────────────────\n\n$b_n=\\dfrac1{a_n}$ なので\n\n$$a_n=\\frac1{b_n}=\\frac1{\\,3^{\\,n}-1\\,}\\qquad(n=1,2,3,\\dots).$$\n\n────────────────\n4　確認  \n────────────────\n\n求めた式が漸化式を満たすか確かめる。\n\n右辺  \n$$\\frac{a_n}{2a_n+3}\n   =\\frac{\\dfrac1{3^n-1}}{\\,\\dfrac2{3^n-1}+3}\n   =\\frac1{3^n-1}\\cdot\\frac{3^n-1}{3^{\\,n+1}-1}\n   =\\frac1{3^{\\,n+1}-1}=a_{n+1}$$\n\nとなり，漸化式を満たす。初項も\n\n$$a_1=\\frac1{3^1-1}=\\frac12$$\n\nで与条件に一致する。\n\n────────────────\n5　結論  \n────────────────\n\n$$\\boxed{\\,a_n=\\dfrac1{3^{\\,n}-1}\\quad(n\\ge1)\\,}$$",
            "is_correct": true
        },
        {
            "statement": "次の条件によって定められる数列 $\\{a_n\\}$ の一般項を求めよ。 $$ a_1 = 10, \\quad a_{n+1} = 2a_n + 2^{n+2} $$",
            "solution": "$$ a_n = ( 2n + 3 ) \\cdot 2^n $$",
            "gpt": "【解答】\n\n求めるのは  \n$$a_{n+1}=2a_n+2^{\\,n+2},\\qquad a_1=10$$  \nを満たす数列 $\\{a_n\\}$ の一般項である。  \n高校数学でよく用いる「置き換え（割り算による簡素化）」を行うと計算がすっきりする。\n\n────────────────────────\n1　等比数列的な部分を取り除く  \n────────────────────────\n右辺には $2a_n$ と $2^{\\,n+2}$ が現れている。両辺を $2^{\\,n+1}$ で割り、  \n$$\\frac{a_{n+1}}{2^{\\,n+1}}=\\frac{a_n}{2^{\\,n}}+2$$  \nと変形する。\n\nここで\n$$b_n=\\frac{a_n}{2^{\\,n}}\\quad(n\\ge1)$$\nとおくと，上式は\n$$b_{n+1}=b_n+2\\qquad(n\\ge1)$$\nとなり，$\\{b_n\\}$ は初項 $b_1=10/2=5$，公差 $2$ の等差数列である。\n\n────────────────────────\n2　等差数列 $\\{b_n\\}$ の一般項  \n────────────────────────\n等差数列の公式より  \n$$b_n=b_1+2(n-1)=5+2n-2=2n+3.$$\n\n────────────────────────\n3　元の数列 $\\{a_n\\}$ へ戻す  \n────────────────────────\n定義 $b_n=a_n/2^{\\,n}$ を用いれば  \n$$a_n=b_n\\cdot2^{\\,n}=(2n+3)2^{\\,n}.$$\n\n────────────────────────\n4　確認（数学的帰納法で裏づけ）  \n────────────────────────\n(i) $n=1$ のとき  \n$a_1=(2\\cdot1+3)2^{\\,1}=5\\cdot2=10$ で初期条件を満たす。  \n\n(ii) $n=k$ で成立すると仮定：$a_k=(2k+3)2^{\\,k}$.  \n    すると  \n    $$\n    a_{k+1}=2a_k+2^{\\,k+2}\n            =2(2k+3)2^{\\,k}+2^{\\,k+2}\n            =(4k+6+4)2^{\\,k}\n            =(4k+10)2^{\\,k}\n            =(2(k+1)+3)2^{\\,k+1}.\n    $$\n    よって $n=k+1$ でも成り立つ。\n\n(i)(ii)よりすべての $n\\in\\mathbb{N}$ で公式は正しい。\n\n────────────────────────\n【結論】  \n数列 $\\{a_n\\}$ の一般項は\n$$\\boxed{\\,a_n=2^{\\,n}(2n+3)\\,}. $$",
            "is_correct": true
        },
        {
            "statement": "次の条件によって定められる数列 $\\{a_n\\}$ の一般項を求めよ。 $$ a_1 = 3, \\quad a_{n+1} = 6a_n + 3^{n+1} $$",
            "solution": "$$ a_n = ( 2^n - 1 ) \\cdot 3^n $$",
            "gpt": "【解答】\n\n数列 $\\{a_n\\}$ は\n\n$$a_{n+1}=6a_n+3^{\\,n+1}\\qquad(n\\ge1),\\qquad a_1=3$$\n\nで定まっています。一次の線形漸化式なので、  \n「斉次解（同次解）」＋「特解」を求める方法で一般項を導きます。\n\n────────────────────────\n1. 斉次方程式の解  \n────────────────────────\n右辺の非同次項 $3^{\\,n+1}$ を 0 とおいた斉次漸化式は\n\n$$a_{n+1}=6a_n.$$\n\nこれは $a_{n}=C\\cdot6^{\\,n-1}$（$C$ は定数）と表されます。\n\n────────────────────────\n2. 特解の設定  \n────────────────────────\n非同次項が $3^{\\,n+1}$（指数関数形）なので，  \n特解を「同じ形」で $a_n^{(p)}=k\\cdot3^{\\,n}$ と仮定します（$k$ は定数）。\n\n仮定を漸化式に代入すると\n\n$$a_{n+1}^{(p)}-6a_n^{(p)}\n=k\\cdot3^{\\,n+1}-6k\\cdot3^{\\,n}=k\\cdot3^{\\,n}(3-6)=-3k\\cdot3^{\\,n}.$$\n\nこの値が右辺の $3^{\\,n+1}=3\\cdot3^{\\,n}$ に一致すればよいので\n\n$$-3k=3 \\quad\\Longrightarrow\\quad k=-1.$$\n\nしたがって特解は\n\n$$a_n^{(p)}=-3^{\\,n}.$$\n\n────────────────────────\n3. 一般解と初期条件の決定  \n────────────────────────\n一般解は\n\n$$a_n = (\\text{斉次解}) + (\\text{特解})\n    = C\\cdot6^{\\,n-1} - 3^{\\,n}.$$\n\n初期条件 $a_1=3$ を代入して定数 $C$ を求めます。\n\n$$3 = C\\cdot6^{\\,0} - 3^{\\,1}=C-3\\quad\\Longrightarrow\\quad C=6.$$\n\n────────────────────────\n4. 結論  \n────────────────────────\nよってすべての $n\\ge1$ について\n\n$$a_n=6^{\\,n}-3^{\\,n}.$$\n\n（検算）  \n$n=1$: $6^{1}-3^{1}=6-3=3$ で初期値に一致。  \n$n\\to n+1$:  \n$a_{n+1}=6^{\\,n+1}-3^{\\,n+1}$  \n　　　　$=6\\bigl(6^{\\,n}-3^{\\,n}\\bigr)+3^{\\,n+1}$  \n　　　　$=6a_n+3^{\\,n+1}$ となり、漸化式を満たすことも確認できます。\n\n以上より、数列 $\\{a_n\\}$ の一般項は $a_n=6^{\\,n}-3^{\\,n}$ です。",
            "is_correct": true
        },
        {
            "statement": "次の条件によって定められる数列 $\\{a_n\\}$ の一般項を求めよ。 $$ a_1 = 1, \\quad a_{n+1} = 2a_n + 3n $$",
            "solution": "$$ a_n = 7 \\cdot 2^{n-1} - 3n - 3 $$",
            "gpt": "【解答】\n\n与えられた漸化式  \n$$a_{n+1}=2a_n+3n\\qquad(n=1,2,3,\\dots),\\qquad a_1=1$$  \nは一次非同次線形漸化式です。以下では高校数学で扱う手法だけを用いて一般項を求めます。\n\n────────────────\n1　同次部分（右辺を 0 とする）の解を求める  \n右辺の $3n$ を無視した同次漸化式は  \n$$a_{n+1}=2a_n$$  \nで、これは等比数列なので  \n$$a_n^{(h)}=C\\cdot2^{\\,n-1}\\qquad(C\\text{ は定数})$$  \nと書けます。\n\n────────────────\n2　非同次部分の特解を求める  \n右辺が $3n$ と 1 次式なので、特解を同じ形  \n$$a_n^{(p)}=\\alpha n+\\beta$$  \nと仮定して係数 $\\alpha,\\beta$ を決めます。\n\n漸化式に代入すると  \n$$\\alpha(n+1)+\\beta=2(\\alpha n+\\beta)+3n$$\n$$\\alpha n+\\alpha+\\beta=2\\alpha n+2\\beta+3n$$\n\n両辺の $n$ の係数と定数項を比較すると\n\\[\n\\begin{cases}\n\\alpha-2\\alpha=3 &\\Longrightarrow\\; -\\alpha=3\\;\\Longrightarrow\\;\\alpha=-3 \\\\\n\\alpha+\\beta-2\\beta=0 &\\Longrightarrow\\; \\alpha-\\beta=0\\;\\Longrightarrow\\;\\beta=-3\n\\end{cases}\n\\]\n\nしたがって特解は  \n$$a_n^{(p)}=-3n-3.$$\n\n────────────────\n3　一般解と初期条件から定数決定  \n一般解は「同次解＋特解」の形になるので\n$$a_n=C\\cdot2^{\\,n-1}-3n-3.$$\n\n初期条件 $a_1=1$ を代入して $C$ を求める：\n$$1=C\\cdot2^{\\,0}-3\\cdot1-3=C-6 \\quad\\Longrightarrow\\quad C=7.$$\n\n────────────────\n4　結論  \nしたがって数列 $\\{a_n\\}$ の一般項は\n$$a_n=7\\cdot2^{\\,n-1}-3n-3\\qquad(n=1,2,3,\\dots).$$\n\n────────────────\n【別解（置換で等比数列化）】  \n$b_n=a_n+3n+3$ とおくと  \n$b_{n+1}=a_{n+1}+3(n+1)+3=2a_n+3n+3n+6=2(a_n+3n+3)=2b_n$  \nより $b_{n+1}=2b_n$、すなわち $b_n$ は初項 $b_1=7$、公比 $2$ の等比数列。  \n$$b_n=7\\cdot2^{\\,n-1}\\quad\\Longrightarrow\\quad a_n=b_n-3n-3=7\\cdot2^{\\,n-1}-3n-3.$$\n\nどちらの方法でも同じ結論を得る。",
            "is_correct": true
        },
        {
            "statement": "次の条件によって定められる数列 $\\{a_n\\}$ の一般項を求めよ。 $$ a_1 = 1, \\quad (n+1)a_{n+1} = na_n $$",
            "solution": "$$ a_n = \\frac{1}{n} $$",
            "gpt": "【解説】\n\n与えられた数列 $\\{a_n\\}$ は  \n$$ (n+1)a_{n+1}=na_n \\qquad(n=1,2,3,\\dots),\\qquad a_1=1 $$  \nという漸化式で定められています。一般項 $a_n$ を求めましょう。\n\n────────────────────────\n1. 漸化式を整理する  \n────────────────────────\n$$a_{n+1}=\\frac{n}{n+1}\\,a_n \\qquad(n\\ge1)$$  \nすなわち「１つ進むごとに $\\displaystyle\\frac{n}{n+1}$ 倍になる」数列です。\n\n────────────────────────\n2. 積の形で書き表す  \n────────────────────────\n$a_1$ から $a_n$ まで順にたどると\n\n$\\displaystyle\n\\begin{aligned}\na_2 &=\\frac{1}{2}a_1,\\\\\na_3 &=\\frac{2}{3}a_2=\\frac{2}{3}\\cdot\\frac{1}{2}a_1,\\\\\n     &\\;\\;\\vdots\\\\\na_n &=\\frac{n-1}{n}\\,a_{n-1}.\n\\end{aligned}$\n\nよって一般に  \n$$a_n\n=a_1\\cdot\\frac{1}{2}\\cdot\\frac{2}{3}\\cdot\\frac{3}{4}\\cdots\\frac{n-1}{n}\n=a_1\\prod_{k=1}^{n-1}\\frac{k}{k+1}.$$\n\n────────────────────────\n3. 積を計算する（望遠鏡型積）  \n────────────────────────\n積の分子・分母を並べると\n\n$\\displaystyle\n\\prod_{k=1}^{n-1}\\frac{k}{k+1}\n=\\frac{\\boxed{1}\\,2\\,3\\cdots(n-1)}\n      {2\\,3\\cdots(n-1)\\,\\boxed{n}}\n=\\frac{1}{n}.$\n\nしたがって  \n$$a_n=a_1\\cdot\\frac{1}{n}=\\frac{1}{n}.$$\n\n────────────────────────\n4. 帰納法による確認（任意の $n$ で成立）\n────────────────────────\n帰納法で確かめておきます。\n\n(1) $n=1$ のとき $a_1=1=\\dfrac1{1}$ で成立。  \n(2) $n$ で $a_n=\\dfrac1n$ が成り立つと仮定すると\n$$a_{n+1}=\\frac{n}{n+1}a_n\n=\\frac{n}{n+1}\\cdot\\frac1n\n=\\frac1{n+1}.$$\nよって $n+1$ でも成立し、数学的帰納法によりすべての $n$ で\n$$a_n=\\frac1n$$\nが成り立ちます。\n\n────────────────────────\n【結論】\n\n一般項は  \n$$\\boxed{\\,a_n=\\dfrac1n\\quad(n=1,2,3,\\dots)\\,}$$  \n\nこれで「ほかに可能性がない」ことも示されました。",
            "is_correct": true
        },
        {
            "statement": "次の条件によって定められる数列 $\\{a_n\\}$ の一般項を求めよ。 $$ a_1 = 1, \\quad na_{n+1} = (n+1)a_n $$",
            "solution": "$$ a_n = n $$",
            "gpt": "【解答】\n\n与えられた漸化式  \n$$na_{n+1}=(n+1)a_n\\qquad(n\\ge1),\\quad a_1=1$$  \nから一般項を求める。\n\n1. 漸化式を整理する  \n   $$a_{n+1}=\\frac{n+1}{n}\\,a_n=\\left(1+\\frac1n\\right)a_n.$$\n\n2. 連続して代入（帰納的積の形へ）\n   $$\n   \\begin{aligned}\n   a_2 &=\\frac{2}{1}a_1,\\\\\n   a_3 &=\\frac{3}{2}a_2=\\frac{3}{2}\\cdot\\frac{2}{1}a_1,\\\\\n   a_4 &=\\frac{4}{3}a_3=\\frac{4}{3}\\cdot\\frac{3}{2}\\cdot\\frac{2}{1}a_1,\\\\\n   &\\ \\ \\vdots\\\\\n   a_n &=\\frac{n}{n-1}\\cdot\\frac{n-1}{n-2}\\cdots\\frac{3}{2}\\cdot\\frac{2}{1}a_1.\n   \\end{aligned}\n   $$\n\n3. 積の telescoping（逐次約分）  \n   右辺の分母と分子がすべて打ち消し合い，最終的に残るのは $n$ だけ：\n   $$a_n=n\\,a_1.$$\n\n4. 初期条件 $a_1=1$ を代入  \n   $$a_n=n\\cdot1=n.$$\n\n5. 確認（数学的帰納法）\n   ⑴ $n=1$ のとき $a_1=1$ で成立。  \n   ⑵ $n=k$ で $a_k=k$ とすると，漸化式より\n   $$ka_{k+1}=(k+1)a_k=(k+1)k\\quad\\Longrightarrow\\quad a_{k+1}=k+1.$$  \n   よって帰納法によりすべての自然数 $n$ で $a_n=n$ が成り立つ。\n\nしたがって，数列 $\\{a_n\\}$ の一般項は\n\n$$\\boxed{a_n=n}\\qquad(n\\ge1).$$",
            "is_correct": true
        },
        {
            "statement": "次の条件によって定められる数列 $ \\{a_n\\} $ の一般項を求めよ。 $$ a_1 = 0, \\quad a_2 = 1, \\quad a_{n+2} + a_{n+1} - 6a_n = 0 $$",
            "solution": "$$ a_n = \\frac{ 2^{n-1} - (-3)^{n-1} }{ 5 } $$",
            "gpt": "【解答】\n\n①　一般解の形を立てる  \n漸化式  \n$$a_{n+2}+a_{n+1}-6a_n=0\\qquad(n\\ge1)$$  \nは「２階同次線形漸化式（係数一定）」なので，  \n$$a_n=Ar_1^{\\,n}+Br_2^{\\,n}$$  \nという形の解が得られます。ここで $r_1,\\;r_2$ は特性方程式の解です。\n\n②　特性方程式を解く  \n漸化式の係数に従って  \n$$r^2+r-6=0$$  \n$$\\;(r+3)(r-2)=0$$  \nより  \n$$r_1=-3,\\qquad r_2=2.$$\n\n③　一般項（文字定数を含む）  \n$$a_n=A(-3)^{\\,n}+B2^{\\,n}\\qquad(\\*).$$\n\n④　初期条件で $A,\\;B$ を決定  \n$n=1,\\;2$ を $(\\*)$ に代入する。\n\n$n=1$:  \n$$a_1=A(-3)+B\\cdot2=0\\;\\Longrightarrow\\;-3A+2B=0\\quad(1)$$\n\n$n=2$:  \n$$a_2=A(-3)^2+B\\cdot2^2=1\\;\\Longrightarrow\\;9A+4B=1\\quad(2)$$\n\n(1) から $B=\\dfrac{3}{2}A$ を (2) に代入。  \n$$9A+4\\left(\\frac{3}{2}A\\right)=9A+6A=15A=1$$  \n$$A=\\frac{1}{15},\\qquad B=\\frac{3}{2}\\cdot\\frac{1}{15}=\\frac{1}{10}.$$\n\n⑤　一般項の決定  \n$$a_n=\\frac{1}{15}(-3)^{\\,n}+\\frac{1}{10}2^{\\,n}\\qquad(n\\ge1).$$\n\n⑥　確認（最初の数項）  \n$n=1$: $\\displaystyle a_1=\\frac{1}{15}(-3)+\\frac{1}{10}\\cdot2=0$  \n$n=2$: $\\displaystyle a_2=\\frac{1}{15}\\cdot9+\\frac{1}{10}\\cdot4=1$  \n$n=3$: $\\displaystyle a_3=\\frac{1}{15}(-27)+\\frac{1}{10}\\cdot8=-\\frac{3}{5}$  \n漸化式 $a_3+a_2-6a_1=0$ も確かに満たす。\n\nしたがって、求める一般項は  \n$$\\boxed{\\,a_n=\\dfrac{1}{15}(-3)^{\\,n}+\\dfrac{1}{10}\\,2^{\\,n}\\,}\\;(n=1,2,3,\\ldots)$$",
            "is_correct": true
        },
        {
            "statement": "次の条件によって定められる数列 $\\{a_n\\}$ の一般項を求めよ。 $$ a_1 = 1, \\quad a_2 = 2, \\quad a_{n+2} + 3a_{n+1} - 4a_n = 0 $$",
            "solution": "$$ a_n = \\frac{ 6 - (-4)^{n-1} }{ 5 } $$",
            "gpt": "解法の方針  \n「 2 次の線形漸化式（定数係数・斉次形）」  \n　→　特性方程式を立て，その解（特性根）から一般項を作る。  \n　→　初期条件 $a_1,\\ a_2$ を代入して定数を決定する。\n\n─────────────────────────────\n1.  特性方程式を求める  \n漸化式  \n$$a_{n+2}+3a_{n+1}-4a_n=0$$  \nに対し，$a_n=r^n$ とおくと\n\n$$r^{n+2}+3r^{n+1}-4r^n=0\n\\quad\\Longleftrightarrow\\quad\nr^n\\bigl(r^2+3r-4\\bigr)=0.$$\n\n$r\\neq0$ なので\n\n$$r^2+3r-4=0.$$\n\n2.  特性根の計算  \n$$r^2+3r-4=(r+4)(r-1)=0\n\\quad\\Longrightarrow\\quad\nr_1=1,\\; r_2=-4.$$\n\n互いに異なる 2 つの実数根をもつので，一般項は\n\n$$a_n=A\\cdot 1^{\\,n}+B\\cdot(-4)^{\\,n}=A+B(-4)^n\n\\quad(n\\ge0).$$\n\n3.  初期条件で $A,\\;B$ を決定  \n(1) $n=1$ のとき  \n$$a_1=A-4B=1.$$\n\n(2) $n=2$ のとき  \n$$a_2=A+16B=2.$$\n\n連立方程式  \n\\[\n\\begin{cases}\nA-4B=1\\\\\nA+16B=2\n\\end{cases}\n\\]\nを解く：\n\n(i) ２式を引くと $20B=1\\;\\Longrightarrow\\;B=\\dfrac1{20}$.  \n(ii) この値を $A-4B=1$ に代入すると  \n$$A=1+4B=1+4\\left(\\dfrac1{20}\\right)=1+\\dfrac15=\\dfrac65.$$\n\n4.  一般項  \n$$a_n=\\frac65+\\frac{(-4)^n}{20}\\quad(n\\ge1).$$\n\n─────────────────────────────\n答え  \n$$\\boxed{\\,a_n=\\dfrac65+\\dfrac{(-4)^n}{20}\\;(n\\ge1)\\,}$$",
            "is_correct": true
        },
        {
            "statement": "次の条件によって定められる数列 $\\{a_n\\}$ の一般項を求めよ。 $$ a_1 = 0, \\quad a_2 = 1, \\quad a_{n+2} + 5a_{n+1} + 6a_n = 0 $$",
            "solution": "$$ a_n = (-2)^{n-1} - (-3)^{n-1} $$",
            "gpt": "【解答】\n\n本数列は  \n$$a_{n+2}+5a_{n+1}+6a_n=0\\qquad(n\\ge1)$$  \nで定まる２次の線形漸化式（係数一定・斉次）なので，  \n$a_n=\\lambda^n$ とおくと次の特性方程式を得る。  \n\n$$\\lambda^{n+2}+5\\lambda^{n+1}+6\\lambda^{n}=0\n\\quad\\Longleftrightarrow\\quad\n\\lambda^2+5\\lambda+6=0$$\n\n特性方程式を解く。  \n\n$$\\lambda^2+5\\lambda+6=(\\lambda+2)(\\lambda+3)=0\n\\quad\\Longrightarrow\\quad\n\\lambda=-2,\\,-3$$\n\n互いに異なる２つの解 $\\lambda_1=-2,\\ \\lambda_2=-3$ が得られたので，一般解は\n\n$$a_n=A(-2)^n+B(-3)^n\\qquad(\\text{定数 }A,B)$$\n\n初期条件 $a_1=0,\\ a_2=1$ を代入して $A,\\;B$ を決める。\n\n① $n=1$ のとき  \n$$0=a_1=-2A-3B \\qquad\\Longrightarrow\\qquad 2A+3B=0\\quad(1)$$\n\n② $n=2$ のとき  \n$$1=a_2=4A+9B \\qquad\\Longrightarrow\\qquad 4A+9B=1\\quad(2)$$\n\n(1) を $A=-\\dfrac32\\,B$ として (2) に代入する。  \n\n$$4\\left(-\\frac32B\\right)+9B=1 \\;\\Longrightarrow\\; -6B+9B=1 \\;\\Longrightarrow\\; 3B=1 \\;\\Longrightarrow\\; B=\\frac13$$\n\n$$A=-\\frac32\\cdot\\frac13=-\\frac12$$\n\nしたがって\n\n$$a_n=-\\frac12(-2)^n+\\frac13(-3)^n\\qquad(n\\ge1)$$\n\n指数部の負号をまとめると\n\n$$a_n=\\bigl(-1\\bigr)^n\\bigl(3^{\\,n-1}-2^{\\,n-1}\\bigr)\\qquad(n\\ge1)$$\n\nこれが求める一般項である。初期値 $n=1,2$ を代入すると確かに $a_1=0,\\ a_2=1$ を満たし，漸化式にも従うことが確認できるので結論は正しい。",
            "is_correct": true
        },
        {
            "statement": "次の条件によって定められる数列 $\\{a_n\\}$ の一般項を求めよ。 $$ a_1 = 1, \\quad a_2 = 4, \\quad a_{n+2} - 6a_{n+1} + 9a_n = 0 $$",
            "solution": "$$ a_n = (n+2) \\cdot 3^{n-2} $$",
            "gpt": "【解答】\n\n1．漸化式の特徴方程式を立てる  \n与えられた漸化式  \n$$a_{n+2}-6a_{n+1}+9a_n=0 \\quad(n\\ge 1)$$  \nは定係数２次線形斉次漸化式なので，  \n$$r^2-6r+9=0$$  \nという特徴方程式を考える。\n\n2．特徴方程式を解く  \n$$r^2-6r+9=(r-3)^2=0$$  \nしたがって重解 $r=3$ を２個もつ。\n\n3．一般解の形  \n重解 $r=3$ の場合，高校数学で学ぶとおり一般項は  \n$$a_n=(\\alpha+\\beta n)3^{\\,n}$$  \nと書ける（$\\alpha,\\beta$ は定数）。  \n指数部分を $3^{n-1}$ などにしてもよいが，ここでは $3^{\\,n}$ を用いる。\n\n4．初期条件で定数を決定する  \n初期条件 $a_1=1,\\;a_2=4$ を代入する。\n\n(1) $n=1$ を代入  \n$$a_1=1\\quad\\Rightarrow\\quad (\\alpha+\\beta)\\,3 =1$$  \n$$\\alpha+\\beta=\\dfrac13\\tag{☆}$$\n\n(2) $n=2$ を代入  \n$$a_2=4\\quad\\Rightarrow\\quad (\\alpha+2\\beta)\\,3^2=4$$  \n$$\\alpha+2\\beta=\\dfrac49\\tag{☆☆}$$\n\n(☆) と (☆☆) を連立すると  \n$$\\beta=\\dfrac19,\\quad\\alpha=\\dfrac23\\cdot\\dfrac13-\\dfrac19=\\dfrac29.$$\n\n5．一般項  \n$$a_n=(\\alpha+\\beta n)3^{\\,n}\n       =\\left(\\dfrac29+\\dfrac19\\,n\\right)3^{\\,n}.$$\n\n分母を消すとさらに簡潔に  \n$$a_n=\\dfrac{n+2}{9}\\,3^{\\,n}= (n+2)3^{\\,n-2}$$  \nとなる。\n\n6．確認（任意）  \n$n=1,2$ を代入すると  \n$$a_1=(1+2)3^{-1}=1,\\qquad a_2=(2+2)3^{0}=4$$  \n確かに初期条件を満たす。\n\nよって，求める一般項は  \n$$\\boxed{\\,a_n=(n+2)3^{\\,n-2}\\,}\\quad(n\\ge1).$$",
            "is_correct": true
        },
        {
            "statement": "次の条件によって定められる数列 $ \\{a_n\\} $ の一般項を求めよ。 $$ a_1 = 5, \\quad a_{n+1} = 8a_n^2 $$",
            "solution": "$$ a_n = \\frac{1}{8} \\cdot {40^2}^{n-1} $$",
            "gpt": "【解答方針】  \n漸化式 $a_{n+1}=8a_n^2$ は「２乗して 8 倍」という非線形な形なので，そのままでは扱いにくい。  \nしかし「対数」を取ることで指数部分が次数 1 の線形漸化式に変わり，簡単に一般項を求めることができる。\n\n────────────────────────────\n1．対数を取って一次漸化式に帰着させる  \n────────────────────────────\n底を 2 とする対数を\n\n$$b_n=\\log_2 a_n$$\n\nと置くと\n\n$$\n\\log_2 a_{n+1}\n =\\log_2(8a_n^2)\n =\\log_2 8+\\log_2(a_n^2)\n =3+2\\log_2 a_n\n =3+2b_n.\n$$\n\nしたがって\n\n$$b_{n+1}=2b_n+3\\qquad(n\\ge 1).$$\n\nこれは一次漸化式（線形漸化式）である。\n\n────────────────────────────\n2．一次漸化式 $b_{n+1}=2b_n+3$ の一般解  \n────────────────────────────\n(1) 同次解  \n　$b_{n+1}=2b_n$ の解は $b_n^{(h)}=C\\cdot 2^n$。\n\n(2) 特解  \n　定数解 $b_n\\equiv k$ と仮定すると  \n　$k=2k+3\\;\\Longrightarrow\\;k=-3$。\n\nよって一般解は\n\n$$b_n=C\\cdot2^{\\,n}-3.$$\n\n初期条件 $a_1=5 \\;\\Rightarrow\\; b_1=\\log_2 5$ を代入すると\n\n$$\\log_2 5=b_1=C\\cdot2^1-3\\Longrightarrow C=\\frac{3+\\log_2 5}{2}.$$\n\nしたがって\n\n$$\nb_n=\\Bigl(\\frac{3+\\log_2 5}{2}\\Bigr)2^{\\,n}-3\n      =(3+\\log_2 5)\\,2^{\\,n-1}-3.\n$$\n\n────────────────────────────\n3．元の数列 $a_n$ に戻す  \n────────────────────────────\n$b_n=\\log_2 a_n$ なので\n\n$$\na_n=2^{\\,b_n}=2^{\\,(3+\\log_2 5)\\,2^{\\,n-1}-3}\n     =2^{-3}\\,2^{\\,(3+\\log_2 5)\\,2^{\\,n-1}}.\n$$\n\nここで指数法則を用いて整理すると\n\n(1) $2^{(3)\\,2^{\\,n-1}}=(2^3)^{2^{\\,n-1}}=8^{\\,2^{\\,n-1}},$\n\n(2) $2^{(\\log_2 5)\\,2^{\\,n-1}}=(2^{\\log_2 5})^{2^{\\,n-1}}=5^{\\,2^{\\,n-1}},$\n\nゆえに\n\n$$\na_n=\\frac{1}{8}\\,8^{\\,2^{\\,n-1}}\\;5^{\\,2^{\\,n-1}}\n     =8^{\\,2^{\\,n-1}-1}\\;5^{\\,2^{\\,n-1}}.\n$$\n\nさらに $8\\cdot5=40$ を用いて一つの累乗にまとめると\n\n$$\n\\boxed{\\,a_n=\\dfrac{40^{\\,2^{\\,n-1}}}{8}\n      =8^{\\,2^{\\,n-1}-1}\\,5^{\\,2^{\\,n-1}}\n      \\quad(n\\ge 1)\\, }.\n$$\n\n────────────────────────────\n4．確認  \n────────────────────────────\nn=1 のとき  \n$a_1=\\dfrac{40^{\\,1}}{8}=5$  で初期値と一致。\n\nn=2 のとき  \n$a_2=\\dfrac{40^{\\,2}}{8}= \\dfrac{1600}{8}=200$,  \nまたは漸化式で $8\\cdot5^2=200$ と一致。\n\nよって求めた一般項は正しい。",
            "is_correct": false
        },
        {
            "statement": "次の条件によって定められる数列 $ \\{a_n\\} $ の一般項を求めよ。 $$ a_1 = 2, \\quad a_{n+1} = a_n + 3 $$",
            "solution": "$$ a_n = 3n - 1 $$",
            "gpt": "【解説】\n\n数列 $\\{a_n\\}$ は  \n$a_1 = 2$, $a_{n+1}=a_n+3\\;(n\\ge 1)$  \nで定められています。これは「隣り合う項の差が一定の数列」、すなわち等差数列です。公差（となりの項との差）は\n\n$d=a_{n+1}-a_n=3$  \n\nです。\n\n等差数列では、初項 $a_1$、公差 $d$ を用いて一般項 $a_n$ が  \n$a_n=a_1+d(n-1)$  \nで表されることを思い出しましょう。そこで\n\n$a_1=2,\\; d=3$  \n\nを代入すると\n\n$a_n = 2 + 3(n-1)$.\n\nあとは括弧を外して整理します。\n\n$$\na_n = 2 + 3n - 3 = 3n - 1.\n$$\n\n【確認（数学的帰納法）】\n\n一般項 $a_n=3n-1$ が本当に条件を満たすことを確かめておきます。\n\n1. (基礎) $n=1$ のとき  \n   $a_1 = 3\\cdot1-1 = 2$ で与えられた条件と一致。\n\n2. (帰納) $n=k$ で $a_k = 3k-1$ と仮定すると  \n   $a_{k+1} = a_k + 3 = (3k-1)+3 = 3(k+1)-1$,  \n   つまり $n=k+1$ でも成り立つ。\n\nしたがって、任意の自然数 $n$ について $a_n=3n-1$ となります。\n\n【結論】\n\n$$\n\\boxed{\\,a_n = 3n - 1\\,(n\\ge 1)\\,}\n$$",
            "is_correct": true
        },
        {
            "statement": "次の条件によって定められる数列 $\\{a_n\\}$ の一般項を求めよ。 $$ a_1 = 1, \\quad a_{n+1} = -2a_n $$",
            "solution": "$$ a_n = (-2)^{n-1} $$",
            "gpt": "【解答】\n\n与えられた数列 $\\{a_n\\}$ は  \n$a_1=1$，$a_{n+1}=-2a_n\\;(n\\ge1)$  \nという漸化式で定義されています。これは「各項がその直前の項に一定の数（ここでは $-2$）を掛けたものになっている」ので、等比数列（公比 $-2$）とみなせます。以下、一般項 $a_n$ を求めます。\n\n1. 観察  \n　$a_2=-2a_1=-2$  \n　$a_3=-2a_2=(-2)(-2)=4$  \n　$a_4=-2a_3=(-2)4=-8$  \n　……  \n　符号が交互に変わり、絶対値は $2,4,8,\\dots$ と $2^{n-1}$ になっています。\n\n2. 帰納的に一般項を予想  \n　$a_n=(-2)^{\\,n-1}$ と予想します。\n\n3. 数学的帰納法による確認  \n　(i) $n=1$ のとき  \n　　$a_1=(-2)^{1-1}=(-2)^0=1$ となり、初期条件と一致。  \n　(ii) $n=k$ で成立すると仮定（帰納法の仮定）  \n　　$a_k=(-2)^{k-1}$.  \n　(iii) $n=k+1$ で確認  \n　　漸化式より $a_{k+1}=-2a_k=-2\\cdot(-2)^{k-1}=(-2)^k$.  \n　　したがって $a_{k+1}=(-2)^k$ は帰納的仮定の形 $(-2)^{(k+1)-1}$ と一致します。\n\n　(i) と (iii) から、すべての自然数 $n$ で  \n　$$a_n=(-2)^{\\,n-1}$$  \n　が成り立ちます。\n\n4. 結論  \n　数列 $\\{a_n\\}$ の一般項は  \n　$$a_n = (-2)^{n-1}\\quad(n\\ge1).$$",
            "is_correct": true
        },
        {
            "statement": "次の条件によって定められる数列 $\\{a_n\\}$ の一般項を求めよ。 $$ a_1 = 3, \\quad a_{n+1} = a_n - 5 $$",
            "solution": "$$ a_n = -5n + 8 $$",
            "gpt": "【解答】\n\n1. 数列の性質を確認  \n　条件 $a_{n+1}=a_n-5$ は，前の項から 5 を引くという規則なので，数列 $\\{a_n\\}$ は公差 $-5$ の等差数列である。\n\n2. 等差数列の一般項の公式  \n　初項を $a_1$，公差を $d$ とすると，等差数列の第 $n$ 項 $a_n$ は  \n　$$a_n = a_1 + (n-1)d$$  \n　で与えられる。\n\n3. 本問に当てはめる  \n　初項 $a_1 = 3$，公差 $d = -5$ だから  \n　$$a_n = 3 + (n-1)(-5).$$\n\n4. 整理  \n　$$a_n = 3 - 5(n-1) = 3 - 5n + 5 = 8 - 5n.$$\n\n5. 結論  \n　数列 $\\{a_n\\}$ の一般項は  \n　$$a_n = 8 - 5n \\quad (n = 1,2,3,\\dots).$$",
            "is_correct": true
        },
        {
            "statement": "次の条件によって定められる数列 $\\{a_n\\}$ の一般項を求めよ。 $$ a_1 = -2, \\quad a_{n+1} = 3a_n $$",
            "solution": "$$ a_n = -2 \\cdot 3^{n-1} $$",
            "gpt": "【解答】\n\n数列 $\\{a_n\\}$ は\n\n$a_1=-2,\\qquad a_{n+1}=3a_n\\quad(n\\ge1)$\n\nと定められています。  \n右辺が前項 $a_n$ の３倍になっているので，これは公比 $3$ の等比数列です。以下では一般項 $a_n$ を導きます。\n\n──────────────────────────  \n1. 帰納的に形を予想する  \n初項とその後の数項を書き出してみます。\n\n$a_1=-2$  \n$a_2=3a_1=3(-2)=-6$  \n$a_3=3a_2=3(-6)=-18$  \n$a_4=3a_3=3(-18)=-54$\n\nこれより\n\n$a_1=-2=-2\\cdot3^{0}$  \n$a_2=-6=-2\\cdot3^{1}$  \n$a_3=-18=-2\\cdot3^{2}$  \n$a_4=-54=-2\\cdot3^{3}$\n\nとなり，$a_n=-2\\cdot3^{\\,n-1}$ が成り立ちそうだと分かります。\n\n──────────────────────────  \n2. 数学的帰納法による確認  \n\n【命題】　$n\\ge1$ について $a_n=-2\\cdot3^{\\,n-1}$。\n\n(1) 基礎ステップ  \n$n=1$ のとき  \n$a_1=-2$ は $-2\\cdot3^{1-1}=-2\\cdot3^{0}=-2$ と一致し，命題は成り立つ。\n\n(2) 帰納ステップ  \nある $k$ で $a_k=-2\\cdot3^{\\,k-1}$ が成り立つと仮定する。  \n漸化式より\n$a_{k+1}=3a_k=3\\bigl(-2\\cdot3^{\\,k-1}\\bigr)=-2\\cdot3^{\\,k}= -2\\cdot3^{(k+1)-1}$\n\nで，$k+1$ に対しても命題が成立する。\n\n(3) 結論  \n(1)(2) により，すべての正の整数 $n$ で命題は真となる。\n\n──────────────────────────  \n3. 一般項  \n\nしたがって数列 $\\{a_n\\}$ の一般項は  \n$$a_n=-2\\cdot3^{\\,n-1}\\qquad(n=1,2,3,\\dots)$$\n\nこれ以外の形は等比数列の性質から存在しません。",
            "is_correct": true
        },
        {
            "statement": "次の条件によって定められる数列 $\\{a_n\\}$ の一般項を求めよ。 $$ a_1 = 3, \\quad a_{n+1} = a_n + 2^n $$",
            "solution": "$$ a_n = 2^n + 1 $$",
            "gpt": "【解答】\n\nまず与えられた漸化式を書き直します。  \n$$a_{n+1}-a_n = 2^n \\qquad(n\\ge 1)$$\n\n右辺だけ n に依存する「階差（かいさ）」の形なので、両辺を $k=1$ から $n$ まで足し合わせて telescoping（差分がつぶれる）させます。\n\n1. 両辺を和で書く  \n   $$\\sum_{k=1}^{\\,n}\\bigl(a_{k+1}-a_k\\bigr)=\\sum_{k=1}^{\\,n}2^k$$\n\n2. 左辺は望み通りほとんどが打ち消し合い、端だけ残る  \n   $$\\sum_{k=1}^{\\,n}(a_{k+1}-a_k)=a_{n+1}-a_1$$\n\n3. 右辺は等比数列の和  \n   $$\\sum_{k=1}^{\\,n}2^k=2\\bigl(2^n-1\\bigr)=2^{n+1}-2$$\n\nよって  \n$$a_{n+1}-a_1 = 2^{\\,n+1}-2$$\n\n初項 $a_1=3$ を代入すると  \n$$a_{n+1}=3+\\bigl(2^{\\,n+1}-2\\bigr)=2^{\\,n+1}+1$$\n\n一般項 $a_n$ を得るため、上式の $n$ を $n-1$ に置き換えると\n\n$$a_n = 2^n + 1 \\qquad(n\\ge 1)$$\n\n【確認（数学的帰納法）】\n\n① $n=1$：$a_1=3$、公式は $2^1+1=3$ で一致。  \n② 帰納法の仮定：$a_n=2^n+1$ とする。  \n③ 漸化式より\n$$a_{n+1}=a_n+2^n=(2^n+1)+2^n=2\\cdot2^n+1=2^{n+1}+1$$\n帰納法によりすべての $n$ で成り立ちます。\n\n【結論】\n\n$$\\boxed{\\,a_n = 2^n + 1\\,(n\\ge 1)\\,}$$",
            "is_correct": true
        },
        {
            "statement": "次の条件によって定められる数列 $\\{a_n\\}$ の一般項を求めよ。 $$ a_1 = 2, \\quad a_{n+1} = a_n + 3^n $$",
            "solution": "$$ a_n = \\frac{ 3^n + 1 }{ 2 } $$",
            "gpt": "【解答】\n\nまず，漸化式を整理してみます。\n\n$a_{n+1}-a_n=3^n \\qquad(n=1,2,3,\\dots)$\n\n左辺は数列の「差分」，右辺は $n$ だけの式ですから，両辺を $n=1$ から $n=N-1$ まで足し合わせると望む一般項が得られます（いわゆる telescoping：望遠鏡和）。\n\n①　両辺を加算  \n$\\displaystyle\\sum_{n=1}^{N-1}(a_{n+1}-a_n)=\\sum_{n=1}^{N-1}3^n$\n\n②　左辺の望遠鏡和  \n$\\displaystyle\\sum_{n=1}^{N-1}(a_{n+1}-a_n)=a_N-a_1$\n\n③　右辺は等比数列の和  \n等比数列 $3,3^2,\\dots,3^{N-1}$ の和は  \n$\\displaystyle\\sum_{n=1}^{N-1}3^n=3\\,\\frac{3^{N-1}-1}{3-1}= \\frac{3^N-3}{2}$\n\n④　①〜③をまとめる  \n$a_N-a_1=\\frac{3^N-3}{2}$\n\n⑤　初項 $a_1=2$ を代入  \n$a_N=2+\\frac{3^N-3}{2}=\\frac{3^N+1}{2}$\n\n変数を $N\\to n$ と書き換えれば\n\n$$a_n=\\frac{3^n+1}{2}\\qquad(n=1,2,3,\\dots)$$\n\n【確認】\n\n・初項  \n$n=1$ で $a_1=\\dfrac{3+1}{2}=2$ ⟹ 与えられた $a_1$ と一致。\n\n・漸化式  \n$a_{n+1}-a_n=\\dfrac{3^{n+1}+1}{2}-\\dfrac{3^{n}+1}{2}=\\dfrac{3^{n}(3-1)}{2}=3^n$ ⟹ 与えられた関係式を満たす。\n\nよって一般項は $a_n=\\dfrac{3^{\\,n}+1}{2}$ で確定。",
            "is_correct": true
        },
        {
            "statement": "次の条件によって定められる数列 $\\{a_n\\}$ の一般項を求めよ。 $$ a_1 = 2, \\quad a_{n+1} = a_n + n^2 + n $$",
            "solution": "$$ a_n = \\frac{1}{3}(n-1)n(n+1) + 2 $$",
            "gpt": "【解答】\n\n(1)　漸化式の確認  \n与えられた数列 $\\{a_n\\}$ は  \n$$a_1 = 2,\\qquad a_{n+1}=a_n+n^2+n\\quad(n\\ge 1)$$  \nで定められている。\n\n(2)　差分をまとめる  \n漸化式を $a_{n+1}-a_n$ という「差分」の形で見れば  \n$$a_{n+1}-a_n = n^2+n = n(n+1).$$  \n\n(3)　階差を足し合わせて一般項を得る  \n$k=1$ から $k=n-1$ までの差分をすべて足し合わせると  \n$$a_n-a_1 = \\sum_{k=1}^{n-1}(a_{k+1}-a_k)\n           = \\sum_{k=1}^{n-1}\\bigl(k^2+k\\bigr)\n           = \\sum_{k=1}^{n-1}k^2+\\sum_{k=1}^{n-1}k.$$\n\n(4)　各種和公式の利用  \n高校数学で学ぶ公式  \n$$\\sum_{k=1}^{m}k = \\frac{m(m+1)}{2},\\qquad\n  \\sum_{k=1}^{m}k^2 = \\frac{m(m+1)(2m+1)}{6}$$  \nを $m=n-1$ として用いる。\n\nすると  \n$$\\sum_{k=1}^{n-1}k = \\frac{(n-1)n}{2},$$  \n$$\\sum_{k=1}^{n-1}k^2 = \\frac{(n-1)n(2n-1)}{6}.$$\n\nよって  \n$$a_n-a_1\n  =\\frac{(n-1)n(2n-1)}{6}+\\frac{(n-1)n}{2}.$$\n\n(5)　計算の整理  \n第２項を通分してまとめる。  \n$$\\frac{(n-1)n(2n-1)}{6}\n +\\frac{(n-1)n}{2}\n =\\frac{(n-1)n\\bigl(2n-1+3\\bigr)}{6}\n =\\frac{(n-1)n(2n+2)}{6}\n =\\frac{2(n-1)n(n+1)}{6}\n =\\frac{(n-1)n(n+1)}{3}.$$\n\n(6)　初項を戻して一般項完成  \n$$a_n = a_1 + \\frac{(n-1)n(n+1)}{3}\n       = 2 + \\frac{(n-1)n(n+1)}{3}\\quad(n\\ge 1).$$\n\n(7)　確認  \n・$n=1$ のとき $a_1 = 2 + 0 = 2$ … 与えられた初項と一致  \n・漸化式 $a_{n+1}=a_n+n^2+n$ も実際に代入して成り立つことが計算により確かめられる。\n\nしたがって、求める一般項は  \n\n$$\\boxed{\\,a_n = 2 + \\dfrac{(n-1)n(n+1)}{3}\\; (n\\ge 1)\\,.}$$",
            "is_correct": true
        },
        {
            "statement": "次の条件によって定められる数列 $\\{a_n\\}$ の一般項を求めよ。 $$ a_1 = 1, \\quad a_{n+1} = 3a_n + 2 $$",
            "solution": "$$ a_n = 2 \\cdot 3^{n-1} - 1 $$",
            "gpt": "【解答】\n\n1. 初項と漸化式  \n　与えられている数列 $\\{a_n\\}$ は  \n$$a_1 = 1,\\qquad a_{n+1}=3a_n+2\\quad(n\\ge1)$$  \nで定義されている。\n\n2. 同次形に変形するための工夫  \n　右辺に「定数 $2$」が付いているため、そのままでは等比型にならない。  \n　そこで\n\n　(Ⅰ) 「定数解（一定の値をとる解）」を探す。  \n　　$a_n=k$ と仮定すると  \n$$k=3k+2\\;\\Longrightarrow\\;-2k=2\\;\\Longrightarrow\\;k=-1.$$\n\n　(Ⅱ) 数列を $-1$ だけ平行移動する。  \n　　$$(\\text{新しい数列})\\;b_n:=a_n+1$$  \n　とおくと\n$$b_{n+1}=a_{n+1}+1=3a_n+2+1=3a_n+3=3(a_n+1)=3b_n.$$\n\n　こうして $b_n$ は初項 $b_1=a_1+1=2$、公比 $3$ の等比数列になった。\n\n3. $b_n$ の一般項  \n　等比数列の公式より\n$$b_n = b_1\\cdot 3^{\\,n-1}=2\\cdot 3^{\\,n-1}\\quad(n\\ge1).$$\n\n4. 元の数列 $a_n$ に戻す  \n　$b_n=a_n+1$ だったから\n$$a_n = b_n-1 = 2\\cdot 3^{\\,n-1}-1\\quad(n\\ge1).$$\n\n5. 初項との一致確認  \n　$n=1$ とすると $a_1=2\\cdot 3^{0}-1=2-1=1$ となり、条件を満たす。\n\n6. 結論  \n　数列 $\\{a_n\\}$ の一般項は  \n$$\\boxed{a_n = 2\\cdot 3^{\\,n-1}-1\\quad(n\\ge1)}.$$\n\nこの形以外の解は、初期条件 $a_1=1$ を満たさないため存在しない。",
            "is_correct": true
        },
        {
            "statement": "次の条件によって定められる数列 $\\{a_n\\}$ の一般項を求めよ。 $$ a_1 = 0, \\quad a_{n+1} = 1 - \\frac{1}{2}a_n $$",
            "solution": "$$ a_n = -\\frac{2}{3} \\cdot \\left(-\\frac{1}{2}\\right)^{n-1} + \\frac{2}{3} $$",
            "gpt": "【解答】\n\n本数列は 1 次の線形漸化式  \n$$a_{n+1}=1-\\frac12a_n\\quad(n\\ge1),\\qquad a_1=0$$  \nで定められています。高校数学の範囲では、次の２通りの考え方が典型的です。\n\n────────────────────────\nⅠ　定常値（固定点）へ平行移動して扱う方法\n────────────────────────\n\n1. 固定点を求める  \n　もし $a_{n+1}=a_n$ となる値 $A$ があれば  \n$$A=1-\\frac12A\\;\\;\\Longrightarrow\\;\\;A=\\frac23.$$\n\n2. 平行移動して新しい数列 $b_n$ を作る  \n$$b_n=a_n-\\frac23.$$\n\n3. $b_n$ の漸化式  \n$$\nb_{n+1}=a_{n+1}-\\frac23\n=\\left(1-\\frac12a_n\\right)-\\frac23\n=-\\frac12\\left(a_n-\\frac23\\right)\n=-\\frac12\\,b_n.\n$$\n\n4. $b_n$ の一般項  \n$$b_{n+1}=-\\frac12\\,b_n\\quad\\Longrightarrow\\quad\nb_n=\\left(-\\frac12\\right)^{\\,n-1}b_1.$$\n\n　初期値 $b_1=a_1-\\dfrac23=-\\dfrac23$ だから  \n$$b_n=\\left(-\\frac12\\right)^{\\,n-1}\\!\\left(-\\frac23\\right)\n=-\\frac23\\left(-\\frac12\\right)^{\\,n-1}.$$\n\n5. 元に戻す  \n$$\na_n=\\frac23+b_n\n=\\frac23-\\frac23\\left(-\\frac12\\right)^{\\,n-1}\n=\\frac23\\bigl(1-\\bigl(-\\tfrac12\\bigr)^{n-1}\\bigr).\n$$\n\n────────────────────────\nⅡ　「特解＋相似形（斉次解）」で解く方法\n────────────────────────\n\n・同次形 $a_{n+1}+\\dfrac12a_n=0$ は等比数列  \n　$a_n=C\\!\\left(-\\dfrac12\\right)^{n-1}$。  \n・特解として定数 $a_n\\equiv\\dfrac23$ が取れる。  \n・よって一般解  \n$$a_n=\\frac23+C\\!\\left(-\\frac12\\right)^{n-1},$$  \n　初期条件 $a_1=0$ から $C=-\\dfrac23$ が決まり、結論は同じ。\n\n────────────────────────\n結論（一般項）\n────────────────────────\n$$\n\\boxed{\\,a_n=\\dfrac23\\Bigl(1-\\bigl(-\\dfrac12\\bigr)^{n-1}\\Bigr)\\qquad(n\\ge1)\\,}.\n$$\n\n（確認）$n=1$ で $a_1=\\dfrac23(1-1)=0$、条件と一致するので正しい。",
            "is_correct": true
        },
        {
            "statement": "次の条件によって定められる数列 $\\{a_n\\}$ の一般項を求めよ。 $$ a_1 = 0, \\quad a_2 = 1, \\quad a_{n+2} = 3a_{n+1} + 10a_n $$",
            "solution": "$$ \\frac{1}{7} \\Bigl\\{ 5^{n-1} - (-2)^{n-1} \\Bigr\\} $$",
            "gpt": "【解答の方針】  \n本題の漸化式は\n\n$$a_{n+2}=3a_{n+1}+10a_n\\qquad(n\\ge1)$$\n\nという２次の線形同次漸化式（係数一定）です。  \nこのタイプは「特性方程式」を立て、その解から一般項を構成するのが標準手順です。\n\n────────────────────────\n1. 特性方程式を立てる  \n────────────────────────\n\n$$a_{n}=r^{\\,n}\\quad\\bigl(r\\neq0\\bigr)$$\n\nと仮定して漸化式に代入すると\n\n$$r^{\\,n+2}=3r^{\\,n+1}+10r^{\\,n} \\Longrightarrow r^{2}-3r-10=0.$$\n\nこれを特性方程式と呼びます。\n\n────────────────────────\n2. 特性方程式を解く  \n────────────────────────\n\n$$r^{2}-3r-10=(r-5)(r+2)=0 \\quad\\Longrightarrow\\quad r=5,\\; -2.$$\n\n重根ではなく異なる２つの解が得られたので，一般解は一次独立な２つの等比数列の線形結合\n\n$$a_n=A\\cdot5^{\\,n}+B\\cdot(-2)^{\\,n}\\qquad(A,Bは定数)$$\n\nとなります。  \nただし問題文は $a_1,a_2$ が与えられているので，添字を揃えるため $n-1$ 乗で書き換えておくと扱いやすくなります：\n\n$$a_n=A\\cdot5^{\\,n-1}+B\\cdot(-2)^{\\,n-1}.$$\n\n────────────────────────\n3. 初期条件で定数を決定  \n────────────────────────\n\n(1) $n=1$ のとき  \n$$a_1=0=A\\cdot5^{\\,0}+B\\cdot(-2)^{\\,0}=A+B\\quad\\Longrightarrow\\quad B=-A.$$\n\n(2) $n=2$ のとき  \n$$a_2=1=A\\cdot5^{\\,1}+B\\cdot(-2)^{\\,1}=5A-2B.$$\n\n上で $B=-A$ と分かったので\n\n$$1=5A-2(-A)=5A+2A=7A\\quad\\Longrightarrow\\quad A=\\frac17,\\;B=-\\frac17.$$\n\n────────────────────────\n4. 一般項の決定  \n────────────────────────\n\n$$a_n=\\frac17\\bigl(5^{\\,n-1}-(-2)^{\\,n-1}\\bigr)\\qquad(n\\ge1).$$\n\n────────────────────────\n5. （念のため）漸化式を満たすことの確認  \n────────────────────────\n\n右辺を $b_n=\\dfrac17(5^{\\,n-1}-(-2)^{\\,n-1})$ と置いて確かめる。\n\n(1) 初期値  \n$b_1=\\dfrac17(1-1)=0,\\;b_2=\\dfrac17(5-(-2))=1$ で確かに $a_1,a_2$ を満たす。\n\n(2) 漸化式  \n$b_{n+2}= \\dfrac17\\!\\left(5^{\\,n+1}-(-2)^{\\,n+1}\\right)$  \n$3b_{n+1}+10b_n= \\dfrac17\\!\\left(3\\cdot5^{\\,n}-3(-2)^{\\,n}+10\\cdot5^{\\,n-1}-10(-2)^{\\,n-1}\\right)  \n=\\dfrac17\\!\\left(5^{\\,n+1}-(-2)^{\\,n+1}\\right)=b_{n+2}.$\n\nゆえに漸化式を満たすことも確認できた。\n\n────────────────────────\n【結論（一般項）】\n\n$$\\boxed{\\,a_n=\\dfrac{5^{\\,n-1}-(-2)^{\\,n-1}}{7}\\qquad(n\\ge1)\\,}$$",
            "is_correct": true
        },
        {
            "statement": "次の条件によって定められる数列 $\\{a_n\\}$ の一般項を求めよ。 $$ a_1 = 1, \\quad a_2 = 4, \\quad a_{n+2} + a_{n+1} - 6a_n = 0 $$",
            "solution": "$$ a_n = \\frac{2}{15}(-3)^n + \\frac{7}{10}2^n $$",
            "gpt": "【解答】\n\n(1)　漸化式を一般的な形にそろえる  \n与えられた漸化式は  \n$$a_{n+2}+a_{n+1}-6a_n=0 \\qquad(n\\ge1)$$  \nである。これは\n\n・次数が 2  \n・係数が定数  \n\nの線形同次漸化式なので，ふつう「特性方程式」を用いて一般項を決定できる。\n\n────────────────────────\n(2)　特性方程式の作成と解\n\n漸化式の $a_{n+k}$ を $r^{\\,n+k}$ に置き換えると\n\n$$r^{\\,n+2}+r^{\\,n+1}-6r^{\\,n}=0$$\n\n両辺を $r^{\\,n}\\;(r\\ne0)$ で割ると\n\n$$r^{2}+r-6=0$$\n\nこれを「特性方程式」と呼ぶ。因数分解すると\n\n$$r^{2}+r-6=(r-2)(r+3)=0$$\n\nしたがって  \n$$r_1=2,\\qquad r_2=-3$$  \nという 2 つの異なる解（重解でない）が得られる。\n\n────────────────────────\n(3)　一般解（定数未定の形）\n\n異なる 2 根が得られた場合，数列 $\\{a_n\\}$ の一般項は\n\n$$a_n = \\alpha\\,(r_1)^{\\,n}+\\beta\\,(r_2)^{\\,n}\n      = \\alpha\\,2^{\\,n}+\\beta(-3)^{\\,n}$$\n\nと表される。ただし $\\alpha,\\beta$ は定数（まだ未定）。\n\n────────────────────────\n(4)　初期条件から $\\alpha,\\beta$ を決定\n\n初項，第二項が\n\n$$a_1=1,\\qquad a_2=4$$  \n\nと分かっているので代入する。\n\n・$n=1$ のとき  \n$\\displaystyle 1 = a_1 = \\alpha\\,2 + \\beta(-3)$\n $\\Longrightarrow\\; 2\\alpha - 3\\beta = 1 \\quad\\cdots(Ⅰ)$\n\n・$n=2$ のとき  \n$\\displaystyle 4 = a_2 = \\alpha\\,2^{2} + \\beta(-3)^{2}\n                = 4\\alpha + 9\\beta$\n $\\Longrightarrow\\; 4\\alpha + 9\\beta = 4 \\quad\\cdots(Ⅱ)$\n\n連立方程式 (Ⅰ)(Ⅱ) を解く。\n\nまず (Ⅰ) を 2 倍すると $4\\alpha - 6\\beta = 2$。  \nこれを (Ⅱ) から引くと\n\n$$ (4\\alpha + 9\\beta) - (4\\alpha - 6\\beta) = 4 - 2\n   \\;\\Longrightarrow\\; 15\\beta = 2\n   \\;\\Longrightarrow\\; \\beta = \\frac{2}{15} $$\n\nこれを (Ⅰ) に戻すと\n\n$$2\\alpha - 3\\left(\\frac{2}{15}\\right)=1\n\\;\\Longrightarrow\\;\n2\\alpha - \\frac{2}{5}=1\n\\;\\Longrightarrow\\;\n2\\alpha = \\frac{7}{5}\n\\;\\Longrightarrow\\;\n\\alpha = \\frac{7}{10}$$\n\n────────────────────────\n(5)　一般項の決定\n\nしたがって $\\alpha,\\beta$ を代入すると\n\n$$a_n = \\frac{7}{10}\\,2^{\\,n}+\\frac{2}{15}\\,(-3)^{\\,n}\\qquad(n\\ge1)$$\n\n────────────────────────\n(6)　確認（任意の $n$ で漸化式を満たすか）\n\n実際にこの $a_n$ を使って左辺  \n$a_{n+2}+a_{n+1}-6a_n$  \nを計算すると，各項が\n$\\displaystyle\\frac{7}{10}2^{\\,n}$ および\n$\\displaystyle\\frac{2}{15}(-3)^{\\,n}$ の線形結合となり，\n特性方程式 $(r-2)(r+3)=0$ を利用して 0 になることが確かめられる\n（詳細計算は省略できるが，疑問なら自分で代入してみよう）。\n\n────────────────────────\n【結論】\n\n数列 $\\{a_n\\}$ の一般項は\n\n$$\\boxed{\\,a_n = \\frac{7}{10}\\,2^{\\,n}+\\frac{2}{15}\\,(-3)^{\\,n}\\quad(n\\ge1)\\,}$$\n\nこれで，初項・第 2 項も条件を満たし，かつ漸化式もすべての $n$ で成立することが確認できた。",
            "is_correct": true
        },
        {
            "statement": "次の条件によって定められる数列 $\\{a_n\\}$ の一般項を求めよ。 $$ a_1 = 0, \\quad a_2 = 1, \\quad a_{n+2} = 8a_{n+1} - 7a_n $$",
            "solution": "$$ a_n = \\frac{1}{6}\\left(7^{n-1} - 1\\right) $$",
            "gpt": "【解答】\n\n(1) 漸化式の形と特性方程式  \n与えられた漸化式は 2 項間の線形同次漸化式です。\n\n$$a_{n+2}=8a_{n+1}-7a_n \\quad (n\\ge1)$$\n\n一般に $a_{n+2}=pa_{n+1}+qa_n$ 型の漸化式は  \n$r^2-pr-q=0$ を特性方程式と呼び，その解を用いて一般項を求めます。  \nここでは\n\n$$r^2-8r+7=0$$\n\nが特性方程式となります。\n\n(2) 特性方程式の解  \n因数分解すると\n\n$$r^2-8r+7=(r-1)(r-7)=0$$\n\nしたがって根は\n\n$$r=1,\\;7$$\n\nであり，重根ではなく異なる 2 つの実数解です。\n\n(3) 一般解の形  \n根が互いに異なるので，一般項は\n\n$$a_n=A\\cdot1^{\\,n}+B\\cdot7^{\\,n}=A+B\\,7^{\\,n}$$\n\nと表せます。ただし $A,B$ は定数です。\n\n(4) 初期条件を用いて定数を決定  \n初期条件\n\n$$a_1=0,\\qquad a_2=1$$\n\nを代入して $A,B$ を求めます。\n\nまず $n=1$ のとき  \n$$0=a_1=A+B\\,7 \\quad\\Longrightarrow\\quad A=-7B$$\n\n次に $n=2$ のとき  \n$$1=a_2=A+B\\,7^{2}=A+49B$$\n\nここで $A=-7B$ を代入すると  \n$$1=(-7B)+49B=42B \\quad\\Longrightarrow\\quad B=\\frac1{42}$$\n\nすると  \n$$A=-7B=-\\frac7{42}=-\\frac16$$\n\n(5) 一般項の決定  \n求めた $A,B$ を一般解 $a_n=A+B7^n$ に代入すると\n\n$$a_n=-\\frac16+\\frac1{42}7^{\\,n}\n       =\\frac{7^{\\,n}-7}{42}$$\n\n(6) 検算  \n$n=1$ では $a_1=\\frac{7-7}{42}=0$  \n$n=2$ では $a_2=\\frac{49-7}{42}=1$  \n漸化式への代入を行っても成立するので式は正しい。\n\n(7) 結論  \n$$\\boxed{\\,a_n=\\dfrac{7^{\\,n}-7}{42}\\; (n\\ge1)\\,}$$\n\nこれが与えられた数列 $\\{a_n\\}$ の一般項である。",
            "is_correct": true
        }
    ],
    "stats": {
        "total": 66,
        "correct": 65
    }
}